{
  "kingdom": 3776,
  "date": "2026-03-10",
  "data": {
    "name": "3776",
    "day": "2026-03-09",
    "collect": 3960978471555,
    "dead": 1186071941,
    "kill": 104593874165,
    "power": 25829501793,
    "t1": 2725513216,
    "t2": 597097504,
    "t3": 628185666,
    "t4": 5916243293,
    "t5": 2058970064,
    "change_collect": -30286636351,
    "change_dead": -10917490,
    "change_kill": -1927949617,
    "change_power": -120757475,
    "change_t1": -33174760,
    "change_t2": -7616380,
    "change_t3": -7752196,
    "change_t4": -129138088,
    "change_t5": -29184612,
    "dt": "2026/03/09",
    "no_radar_data": 1
  }
}