{
  "kingdom": 1750,
  "from_date": "2025-09-08",
  "to_date": "2026-03-06",
  "data": [
    {
      "id": "62858320",
      "name": "JmAn",
      "max_power": 117196840,
      "power": 110361560,
      "collect": 1300023269,
      "dead": 1440194,
      "kill": 389246359,
      "t1": 2295,
      "t2": 6509,
      "t3": 6013,
      "t4": 16462215,
      "t5": 11229334,
      "help": 7267,
      "dt": "2026/03/06",
      "dead_t1": 0,
      "dead_t2": 0,
      "dead_t3": 0,
      "dead_t4": 0,
      "dead_t5": 1369306
    },
    {
      "id": "58534240",
      "name": "Jackal ᵛᴷ",
      "max_power": 105248865,
      "power": 105248865,
      "collect": 1830512172,
      "dead": 461880,
      "kill": 85789502,
      "t1": 36920,
      "t2": 216,
      "t3": 3474,
      "t4": 2838215,
      "t5": 2869282,
      "help": 5755,
      "dt": "2026/03/06",
      "dead_t1": 0,
      "dead_t2": 0,
      "dead_t3": 0,
      "dead_t4": 0,
      "dead_t5": 77970
    },
    {
      "id": "38501097",
      "name": "Ƒɑdɑ",
      "max_power": 98527490,
      "power": 98527490,
      "collect": 94891013,
      "dead": 0,
      "kill": 35190,
      "t1": 0,
      "t2": 0,
      "t3": 0,
      "t4": 3519,
      "t5": 0,
      "help": 561,
      "dt": "2026/03/06",
      "dead_t1": 0,
      "dead_t2": 0,
      "dead_t3": 0,
      "dead_t4": 0,
      "dead_t5": 0
    },
    {
      "id": "18135072",
      "name": "Stefan Jovke",
      "max_power": 104246478,
      "power": 98034836,
      "collect": 2644834326,
      "dead": 5172919,
      "kill": 128640352,
      "t1": 3327792,
      "t2": 231,
      "t3": 2253,
      "t4": 5996304,
      "t5": 3400114,
      "help": 3707,
      "dt": "2026/03/06",
      "dead_t1": 106637,
      "dead_t2": 825127,
      "dead_t3": 0,
      "dead_t4": 474031,
      "dead_t5": 3681856
    },
    {
      "id": "48726612",
      "name": "Vladik37ᵛᴷ",
      "max_power": 126221391,
      "power": 96010029,
      "collect": 2535927155,
      "dead": 1023394,
      "kill": 691303818,
      "t1": 6474260,
      "t2": 651272,
      "t3": 221243,
      "t4": 16470507,
      "t5": 26155819,
      "help": 720,
      "dt": "2026/03/06",
      "dead_t1": 3912,
      "dead_t2": 26,
      "dead_t3": 0,
      "dead_t4": 6,
      "dead_t5": 726259
    },
    {
      "id": "63019814",
      "name": "Coobraᴴᴼᵀ",
      "max_power": 103241608,
      "power": 95140522,
      "collect": 2839858435,
      "dead": 506694,
      "kill": 297733228,
      "t1": 182,
      "t2": 2122,
      "t3": 18372,
      "t4": 2569866,
      "t5": 13597840,
      "help": 1888,
      "dt": "2026/03/06",
      "dead_t1": 0,
      "dead_t2": 0,
      "dead_t3": 0,
      "dead_t4": 93094,
      "dead_t5": 413600
    },
    {
      "id": "63819345",
      "name": "ᴵᴰKaido",
      "max_power": 111521240,
      "power": 93555355,
      "collect": 3159188390,
      "dead": 5169301,
      "kill": 396375486,
      "t1": 144111,
      "t2": 17633,
      "t3": 10297,
      "t4": 7184425,
      "t5": 16221298,
      "help": 3389,
      "dt": "2026/03/06",
      "dead_t1": 4903,
      "dead_t2": 358409,
      "dead_t3": 0,
      "dead_t4": 0,
      "dead_t5": 4717951
    },
    {
      "id": "52219153",
      "name": "鞑靼一世",
      "max_power": 92839170,
      "power": 92803250,
      "collect": 2777023861,
      "dead": 0,
      "kill": 329680,
      "t1": 0,
      "t2": 0,
      "t3": 0,
      "t4": 0,
      "t5": 16484,
      "help": 543,
      "dt": "2026/03/06",
      "dead_t1": 0,
      "dead_t2": 0,
      "dead_t3": 0,
      "dead_t4": 0,
      "dead_t5": 0
    },
    {
      "id": "49183784",
      "name": "Crank the Tank",
      "max_power": 93014822,
      "power": 86825722,
      "collect": 3180062479,
      "dead": 1011150,
      "kill": 210707614,
      "t1": 57129,
      "t2": 25006,
      "t3": 1559,
      "t4": 2377426,
      "t5": 9343284,
      "help": 3513,
      "dt": "2026/03/06",
      "dead_t1": 0,
      "dead_t2": 0,
      "dead_t3": 0,
      "dead_t4": 0,
      "dead_t5": 769050
    },
    {
      "id": "64094575",
      "name": "Raden Antawirya",
      "max_power": 93106724,
      "power": 83368100,
      "collect": 3544898423,
      "dead": 1895475,
      "kill": 154436438,
      "t1": 257,
      "t2": 26,
      "t3": 18296,
      "t4": 2529723,
      "t5": 6453296,
      "help": 3922,
      "dt": "2026/03/06",
      "dead_t1": 6535,
      "dead_t2": 7509,
      "dead_t3": 611,
      "dead_t4": 140279,
      "dead_t5": 1610150
    },
    {
      "id": "62827383",
      "name": "PhatAD the 2nd",
      "max_power": 97536031,
      "power": 81355060,
      "collect": 2528856946,
      "dead": 755766,
      "kill": 97118056,
      "t1": 34040,
      "t2": 21815,
      "t3": 3362,
      "t4": 1120747,
      "t5": 4292335,
      "help": 2885,
      "dt": "2026/03/06",
      "dead_t1": 0,
      "dead_t2": 0,
      "dead_t3": 0,
      "dead_t4": 3119,
      "dead_t5": 437029
    },
    {
      "id": "45073939",
      "name": "乂  Apocalypse",
      "max_power": 122179496,
      "power": 81099619,
      "collect": 2947827349,
      "dead": 1784495,
      "kill": 280734556,
      "t1": 350730,
      "t2": 259616,
      "t3": 678407,
      "t4": 11242593,
      "t5": 8250281,
      "help": 4169,
      "dt": "2026/03/06",
      "dead_t1": 0,
      "dead_t2": 0,
      "dead_t3": 0,
      "dead_t4": 154333,
      "dead_t5": 729747
    },
    {
      "id": "52183084",
      "name": "MESᴷ乂",
      "max_power": 80428440,
      "power": 80428440,
      "collect": 1436100710,
      "dead": 192741,
      "kill": 69533120,
      "t1": 28501099,
      "t2": 4306,
      "t3": 147,
      "t4": 4484244,
      "t5": 949063,
      "help": 4160,
      "dt": "2026/03/06",
      "dead_t1": 0,
      "dead_t2": 0,
      "dead_t3": 0,
      "dead_t4": 0,
      "dead_t5": 23582
    },
    {
      "id": "49119257",
      "name": "Cranks Gxᵛᴷ",
      "max_power": 82949241,
      "power": 78757767,
      "collect": 1606898510,
      "dead": 0,
      "kill": 4726430,
      "t1": 0,
      "t2": 0,
      "t3": 0,
      "t4": 3049,
      "t5": 234797,
      "help": 589,
      "dt": "2026/03/06",
      "dead_t1": 0,
      "dead_t2": 0,
      "dead_t3": 0,
      "dead_t4": 0,
      "dead_t5": 0
    },
    {
      "id": "35233050",
      "name": "AsaomiShinigami",
      "max_power": 76511939,
      "power": 76475419,
      "collect": 958111799,
      "dead": 0,
      "kill": 2878275,
      "t1": 777,
      "t2": 0,
      "t3": 0,
      "t4": 263138,
      "t5": 12337,
      "help": 698,
      "dt": "2026/03/06",
      "dead_t1": 0,
      "dead_t2": 0,
      "dead_t3": 0,
      "dead_t4": 0,
      "dead_t5": 0
    },
    {
      "id": "111221441",
      "name": "LōōtCōqk",
      "max_power": 87743199,
      "power": 73642837,
      "collect": 1504013372,
      "dead": 141722,
      "kill": 28711946,
      "t1": 278827,
      "t2": 855,
      "t3": 66735,
      "t4": 2823203,
      "t5": 7775,
      "help": 36,
      "dt": "2026/03/06",
      "dead_t1": 0,
      "dead_t2": 0,
      "dead_t3": 0,
      "dead_t4": 0,
      "dead_t5": 84051
    },
    {
      "id": "23448202",
      "name": "Smithᵛᴷ",
      "max_power": 110451036,
      "power": 70753842,
      "collect": 101568582,
      "dead": 0,
      "kill": 260760,
      "t1": 0,
      "t2": 0,
      "t3": 0,
      "t4": 0,
      "t5": 13038,
      "help": 106,
      "dt": "2026/03/06",
      "dead_t1": 0,
      "dead_t2": 0,
      "dead_t3": 0,
      "dead_t4": 0,
      "dead_t5": 0
    },
    {
      "id": "88208885",
      "name": "义ＡＣＥ义",
      "max_power": 69870747,
      "power": 66599405,
      "collect": 1148473037,
      "dead": 1395373,
      "kill": 23842736,
      "t1": 296490,
      "t2": 172626,
      "t3": 39,
      "t4": 1045169,
      "t5": 649317,
      "help": 1227,
      "dt": "2026/03/06",
      "dead_t1": 0,
      "dead_t2": 267387,
      "dead_t3": 0,
      "dead_t4": 35610,
      "dead_t5": 1088275
    },
    {
      "id": "70807862",
      "name": "鞑靼二世",
      "max_power": 66454376,
      "power": 65695124,
      "collect": 2832669079,
      "dead": 576235,
      "kill": 3046380,
      "t1": 0,
      "t2": 0,
      "t3": 0,
      "t4": 0,
      "t5": 152319,
      "help": 514,
      "dt": "2026/03/06",
      "dead_t1": 0,
      "dead_t2": 0,
      "dead_t3": 0,
      "dead_t4": 153131,
      "dead_t5": 423104
    },
    {
      "id": "89442386",
      "name": "魇Morgana",
      "max_power": 63757537,
      "power": 63757537,
      "collect": 159199081,
      "dead": 41788,
      "kill": 4062712,
      "t1": 171,
      "t2": 439,
      "t3": 165,
      "t4": 66152,
      "t5": 169981,
      "help": 77,
      "dt": "2026/03/06",
      "dead_t1": 0,
      "dead_t2": 0,
      "dead_t3": 0,
      "dead_t4": 0,
      "dead_t5": 0
    },
    {
      "id": "52353432",
      "name": "War Lady",
      "max_power": 63669571,
      "power": 63669571,
      "collect": 468260490,
      "dead": 0,
      "kill": 136173,
      "t1": 100783,
      "t2": 2318,
      "t3": 0,
      "t4": 1846,
      "t5": 4646,
      "help": 36,
      "dt": "2026/03/06",
      "dead_t1": 0,
      "dead_t2": 0,
      "dead_t3": 0,
      "dead_t4": 0,
      "dead_t5": 0
    },
    {
      "id": "49849159",
      "name": "Max 163",
      "max_power": 65642540,
      "power": 62772939,
      "collect": 392533059,
      "dead": 0,
      "kill": 0,
      "t1": 0,
      "t2": 0,
      "t3": 0,
      "t4": 0,
      "t5": 0,
      "help": 0,
      "dt": "2026/03/06",
      "dead_t1": 0,
      "dead_t2": 0,
      "dead_t3": 0,
      "dead_t4": 0,
      "dead_t5": 0
    },
    {
      "id": "116566629",
      "name": "One HiT KicK",
      "max_power": 63619589,
      "power": 62261773,
      "collect": 3181471272,
      "dead": 2675693,
      "kill": 135934087,
      "t1": 413835,
      "t2": 5888,
      "t3": 14966,
      "t4": 2013656,
      "t5": 5782156,
      "help": 3085,
      "dt": "2026/03/06",
      "dead_t1": 378810,
      "dead_t2": 0,
      "dead_t3": 54013,
      "dead_t4": 1930593,
      "dead_t5": 276022
    },
    {
      "id": "170655505",
      "name": "HulkTheVet",
      "max_power": 61865695,
      "power": 61556007,
      "collect": 1928947313,
      "dead": 409699,
      "kill": 12953163,
      "t1": 68136,
      "t2": 1371,
      "t3": 5831,
      "t4": 356149,
      "t5": 467599,
      "help": 1446,
      "dt": "2026/03/06",
      "dead_t1": 0,
      "dead_t2": 0,
      "dead_t3": 0,
      "dead_t4": 272738,
      "dead_t5": 19812
    },
    {
      "id": "88276265",
      "name": "gov26",
      "max_power": 58220940,
      "power": 57781298,
      "collect": 36000633,
      "dead": 1236787,
      "kill": 13904631,
      "t1": 17355,
      "t2": 0,
      "t3": 0,
      "t4": 1324346,
      "t5": 32885,
      "help": 372,
      "dt": "2026/03/06",
      "dead_t1": 276808,
      "dead_t2": 364840,
      "dead_t3": 297918,
      "dead_t4": 233453,
      "dead_t5": 63768
    },
    {
      "id": "101596030",
      "name": "Cranks Jr",
      "max_power": 57737469,
      "power": 57728629,
      "collect": 1150232192,
      "dead": 0,
      "kill": 1275900,
      "t1": 0,
      "t2": 0,
      "t3": 0,
      "t4": 0,
      "t5": 63795,
      "help": 304,
      "dt": "2026/03/06",
      "dead_t1": 0,
      "dead_t2": 0,
      "dead_t3": 0,
      "dead_t4": 0,
      "dead_t5": 0
    },
    {
      "id": "63026609",
      "name": "KrakFarm",
      "max_power": 57073203,
      "power": 57073203,
      "collect": 0,
      "dead": 0,
      "kill": 0,
      "t1": 0,
      "t2": 0,
      "t3": 0,
      "t4": 0,
      "t5": 0,
      "help": 1,
      "dt": "2026/03/06",
      "dead_t1": 0,
      "dead_t2": 0,
      "dead_t3": 0,
      "dead_t4": 0,
      "dead_t5": 0
    },
    {
      "id": "68309466",
      "name": "EIEIO",
      "max_power": 56449425,
      "power": 56449425,
      "collect": 1342647949,
      "dead": 0,
      "kill": 5871000,
      "t1": 0,
      "t2": 0,
      "t3": 0,
      "t4": 170,
      "t5": 293465,
      "help": 332,
      "dt": "2026/03/06",
      "dead_t1": 0,
      "dead_t2": 0,
      "dead_t3": 0,
      "dead_t4": 0,
      "dead_t5": 0
    },
    {
      "id": "52159908",
      "name": "Rp30",
      "max_power": 55193630,
      "power": 55008033,
      "collect": 393028043,
      "dead": 416909,
      "kill": 1868950,
      "t1": 0,
      "t2": 0,
      "t3": 0,
      "t4": 10527,
      "t5": 88184,
      "help": 0,
      "dt": "2026/03/06",
      "dead_t1": 2074,
      "dead_t2": 0,
      "dead_t3": 0,
      "dead_t4": 414835,
      "dead_t5": 0
    },
    {
      "id": "128779208",
      "name": "FeltOne",
      "max_power": 75879025,
      "power": 53195116,
      "collect": 6356700,
      "dead": 0,
      "kill": 0,
      "t1": 0,
      "t2": 0,
      "t3": 0,
      "t4": 0,
      "t5": 0,
      "help": 6,
      "dt": "2026/03/06",
      "dead_t1": 0,
      "dead_t2": 0,
      "dead_t3": 0,
      "dead_t4": 0,
      "dead_t5": 0
    },
    {
      "id": "59640892",
      "name": "Jman918",
      "max_power": 50929123,
      "power": 50683423,
      "collect": 1123948325,
      "dead": 197176,
      "kill": 1427760,
      "t1": 0,
      "t2": 0,
      "t3": 0,
      "t4": 626,
      "t5": 71075,
      "help": 240,
      "dt": "2026/03/06",
      "dead_t1": 0,
      "dead_t2": 0,
      "dead_t3": 0,
      "dead_t4": 197596,
      "dead_t5": 0
    },
    {
      "id": "179333032",
      "name": "OTTOMANeEMPİRE",
      "max_power": 46994272,
      "power": 46389659,
      "collect": 2736381281,
      "dead": 2625510,
      "kill": 97226160,
      "t1": 821368,
      "t2": 188488,
      "t3": 468060,
      "t4": 5612813,
      "t5": 1934227,
      "help": 1707,
      "dt": "2026/03/06",
      "dead_t1": 1473857,
      "dead_t2": 0,
      "dead_t3": 0,
      "dead_t4": 991293,
      "dead_t5": 0
    },
    {
      "id": "52356618",
      "name": "Ludwig2308",
      "max_power": 45679275,
      "power": 44006271,
      "collect": 624319206,
      "dead": 1963087,
      "kill": 3755779,
      "t1": 21804,
      "t2": 1744,
      "t3": 2100,
      "t4": 43745,
      "t5": 165104,
      "help": 264,
      "dt": "2026/03/06",
      "dead_t1": 0,
      "dead_t2": 0,
      "dead_t3": 0,
      "dead_t4": 1227074,
      "dead_t5": 0
    },
    {
      "id": "36910973",
      "name": "HappyDo",
      "max_power": 43573608,
      "power": 43571568,
      "collect": 760828059,
      "dead": 0,
      "kill": 354720,
      "t1": 0,
      "t2": 0,
      "t3": 0,
      "t4": 3696,
      "t5": 15888,
      "help": 343,
      "dt": "2026/03/06",
      "dead_t1": 0,
      "dead_t2": 0,
      "dead_t3": 0,
      "dead_t4": 0,
      "dead_t5": 0
    },
    {
      "id": "174400068",
      "name": "HulkTheVet Farm",
      "max_power": 43265373,
      "power": 43264481,
      "collect": 1775539492,
      "dead": 19717,
      "kill": 279380,
      "t1": 0,
      "t2": 0,
      "t3": 0,
      "t4": 0,
      "t5": 13969,
      "help": 480,
      "dt": "2026/03/06",
      "dead_t1": 0,
      "dead_t2": 0,
      "dead_t3": 0,
      "dead_t4": 19862,
      "dead_t5": 0
    },
    {
      "id": "179072933",
      "name": "ᵂᴹHereWolf",
      "max_power": 41302522,
      "power": 41302522,
      "collect": 892105670,
      "dead": 537783,
      "kill": 152190110,
      "t1": 1971928,
      "t2": 6069,
      "t3": 66829,
      "t4": 12498471,
      "t5": 1326578,
      "help": 1253,
      "dt": "2026/03/06",
      "dead_t1": 0,
      "dead_t2": 0,
      "dead_t3": 0,
      "dead_t4": 450516,
      "dead_t5": 0
    },
    {
      "id": "52145640",
      "name": "総督52145640",
      "max_power": 42435724,
      "power": 39975241,
      "collect": 655932347,
      "dead": 1386930,
      "kill": 3434170,
      "t1": 0,
      "t2": 0,
      "t3": 0,
      "t4": 27701,
      "t5": 157858,
      "help": 188,
      "dt": "2026/03/06",
      "dead_t1": 1052,
      "dead_t2": 90,
      "dead_t3": 14,
      "dead_t4": 1385774,
      "dead_t5": 0
    },
    {
      "id": "82213253",
      "name": "Coobster",
      "max_power": 45355216,
      "power": 39190808,
      "collect": 2594078530,
      "dead": 0,
      "kill": 177070,
      "t1": 0,
      "t2": 0,
      "t3": 0,
      "t4": 8767,
      "t5": 4470,
      "help": 535,
      "dt": "2026/03/06",
      "dead_t1": 0,
      "dead_t2": 0,
      "dead_t3": 0,
      "dead_t4": 0,
      "dead_t5": 0
    },
    {
      "id": "70019043",
      "name": "tHEqUEEN",
      "max_power": 39057071,
      "power": 39055087,
      "collect": 1100797148,
      "dead": 827079,
      "kill": 1230850,
      "t1": 0,
      "t2": 0,
      "t3": 0,
      "t4": 1055,
      "t5": 61015,
      "help": 327,
      "dt": "2026/03/06",
      "dead_t1": 0,
      "dead_t2": 0,
      "dead_t3": 0,
      "dead_t4": 261916,
      "dead_t5": 0
    },
    {
      "id": "61924885",
      "name": "SUISIDE",
      "max_power": 45560712,
      "power": 38249235,
      "collect": 959917133,
      "dead": 2495741,
      "kill": 7518940,
      "t1": 0,
      "t2": 0,
      "t3": 0,
      "t4": 0,
      "t5": 375947,
      "help": 192,
      "dt": "2026/03/06",
      "dead_t1": 150550,
      "dead_t2": 0,
      "dead_t3": 0,
      "dead_t4": 2345191,
      "dead_t5": 0
    },
    {
      "id": "60643601",
      "name": "Mini Muffins",
      "max_power": 44749769,
      "power": 37981761,
      "collect": 1084459070,
      "dead": 2411217,
      "kill": 8196300,
      "t1": 0,
      "t2": 0,
      "t3": 0,
      "t4": 0,
      "t5": 409815,
      "help": 225,
      "dt": "2026/03/06",
      "dead_t1": 152900,
      "dead_t2": 0,
      "dead_t3": 0,
      "dead_t4": 2259513,
      "dead_t5": 0
    },
    {
      "id": "142855228",
      "name": "JacRanch ᵛᴷ",
      "max_power": 37873821,
      "power": 37870625,
      "collect": 1088474172,
      "dead": 0,
      "kill": 2818400,
      "t1": 0,
      "t2": 0,
      "t3": 0,
      "t4": 0,
      "t5": 140920,
      "help": 309,
      "dt": "2026/03/06",
      "dead_t1": 0,
      "dead_t2": 0,
      "dead_t3": 0,
      "dead_t4": 0,
      "dead_t5": 0
    },
    {
      "id": "52181179",
      "name": "سجاد الكناني",
      "max_power": 38072470,
      "power": 36490186,
      "collect": 12890178,
      "dead": 1100592,
      "kill": 1353590,
      "t1": 0,
      "t2": 0,
      "t3": 0,
      "t4": 3961,
      "t5": 65699,
      "help": 12,
      "dt": "2026/03/06",
      "dead_t1": 993,
      "dead_t2": 0,
      "dead_t3": 15,
      "dead_t4": 1099672,
      "dead_t5": 0
    },
    {
      "id": "59971463",
      "name": "MESᴷC",
      "max_power": 35917784,
      "power": 35379689,
      "collect": 984100493,
      "dead": 33555,
      "kill": 1407914,
      "t1": 8,
      "t2": 8,
      "t3": 44,
      "t4": 58244,
      "t5": 41264,
      "help": 404,
      "dt": "2026/03/06",
      "dead_t1": 0,
      "dead_t2": 0,
      "dead_t3": 0,
      "dead_t4": 0,
      "dead_t5": 0
    },
    {
      "id": "178917854",
      "name": "ᵂᴹSнanᴋs",
      "max_power": 33846990,
      "power": 33846990,
      "collect": 173840037,
      "dead": 193174,
      "kill": 10644705,
      "t1": 40546,
      "t2": 0,
      "t3": 144,
      "t4": 473342,
      "t5": 295130,
      "help": 80,
      "dt": "2026/03/06",
      "dead_t1": 168133,
      "dead_t2": 0,
      "dead_t3": 0,
      "dead_t4": 25041,
      "dead_t5": 0
    },
    {
      "id": "52988620",
      "name": "乂 Apocalypse2",
      "max_power": 33747288,
      "power": 33747288,
      "collect": 2687148193,
      "dead": 0,
      "kill": 119470,
      "t1": 0,
      "t2": 0,
      "t3": 0,
      "t4": 175,
      "t5": 5886,
      "help": 420,
      "dt": "2026/03/06",
      "dead_t1": 0,
      "dead_t2": 0,
      "dead_t3": 0,
      "dead_t4": 0,
      "dead_t5": 0
    },
    {
      "id": "63424423",
      "name": "MESᴷM",
      "max_power": 33437755,
      "power": 33437755,
      "collect": 1073138614,
      "dead": 0,
      "kill": 1368480,
      "t1": 0,
      "t2": 0,
      "t3": 0,
      "t4": 11680,
      "t5": 62584,
      "help": 442,
      "dt": "2026/03/06",
      "dead_t1": 0,
      "dead_t2": 0,
      "dead_t3": 0,
      "dead_t4": 0,
      "dead_t5": 0
    },
    {
      "id": "24548314",
      "name": "Stefanopolis",
      "max_power": 32279378,
      "power": 32279378,
      "collect": 495643870,
      "dead": 82899,
      "kill": 1180440,
      "t1": 0,
      "t2": 0,
      "t3": 0,
      "t4": 0,
      "t5": 59022,
      "help": 174,
      "dt": "2026/03/06",
      "dead_t1": 0,
      "dead_t2": 0,
      "dead_t3": 0,
      "dead_t4": 81691,
      "dead_t5": 0
    },
    {
      "id": "52227581",
      "name": "PowerPatte",
      "max_power": 34043258,
      "power": 32255641,
      "collect": 24227525,
      "dead": 1099330,
      "kill": 1741890,
      "t1": 0,
      "t2": 0,
      "t3": 0,
      "t4": 14321,
      "t5": 79934,
      "help": 30,
      "dt": "2026/03/06",
      "dead_t1": 329098,
      "dead_t2": 345522,
      "dead_t3": 84854,
      "dead_t4": 339856,
      "dead_t5": 0
    },
    {
      "id": "48746325",
      "name": "VLados",
      "max_power": 30885652,
      "power": 30885652,
      "collect": 798255390,
      "dead": 80985,
      "kill": 831401,
      "t1": 196554,
      "t2": 0,
      "t3": 0,
      "t4": 3301,
      "t5": 37954,
      "help": 38,
      "dt": "2026/03/06",
      "dead_t1": 0,
      "dead_t2": 0,
      "dead_t3": 0,
      "dead_t4": 0,
      "dead_t5": 0
    },
    {
      "id": "6269592",
      "name": "SUMMERWIND",
      "max_power": 33582311,
      "power": 30821385,
      "collect": 6024375,
      "dead": 0,
      "kill": 0,
      "t1": 0,
      "t2": 0,
      "t3": 0,
      "t4": 0,
      "t5": 0,
      "help": 2,
      "dt": "2026/03/06",
      "dead_t1": 0,
      "dead_t2": 0,
      "dead_t3": 0,
      "dead_t4": 0,
      "dead_t5": 0
    },
    {
      "id": "95977372",
      "name": "PhatAD the 3rd",
      "max_power": 30522333,
      "power": 30522333,
      "collect": 1562774893,
      "dead": 0,
      "kill": 0,
      "t1": 0,
      "t2": 0,
      "t3": 0,
      "t4": 0,
      "t5": 0,
      "help": 3,
      "dt": "2026/03/06",
      "dead_t1": 0,
      "dead_t2": 0,
      "dead_t3": 0,
      "dead_t4": 0,
      "dead_t5": 0
    },
    {
      "id": "63698962",
      "name": "乂 Apocalypse3",
      "max_power": 27420299,
      "power": 27398177,
      "collect": 1145245469,
      "dead": 0,
      "kill": 168220,
      "t1": 0,
      "t2": 0,
      "t3": 0,
      "t4": 0,
      "t5": 8411,
      "help": 27,
      "dt": "2026/03/06",
      "dead_t1": 0,
      "dead_t2": 0,
      "dead_t3": 0,
      "dead_t4": 0,
      "dead_t5": 0
    },
    {
      "id": "157702767",
      "name": "Jmuffin",
      "max_power": 26796575,
      "power": 26620384,
      "collect": 1344870134,
      "dead": 866201,
      "kill": 1107265,
      "t1": 389,
      "t2": 0,
      "t3": 952,
      "t4": 0,
      "t5": 55169,
      "help": 41,
      "dt": "2026/03/06",
      "dead_t1": 0,
      "dead_t2": 0,
      "dead_t3": 0,
      "dead_t4": 392000,
      "dead_t5": 0
    },
    {
      "id": "84202787",
      "name": "Darknight113239",
      "max_power": 28782588,
      "power": 24651411,
      "collect": 3449156040,
      "dead": 0,
      "kill": 0,
      "t1": 0,
      "t2": 0,
      "t3": 0,
      "t4": 0,
      "t5": 0,
      "help": 20,
      "dt": "2026/03/06",
      "dead_t1": 0,
      "dead_t2": 0,
      "dead_t3": 0,
      "dead_t4": 0,
      "dead_t5": 0
    },
    {
      "id": "123573685",
      "name": "OnE farm 1",
      "max_power": 23907536,
      "power": 23714084,
      "collect": 1138773278,
      "dead": 55013,
      "kill": 1346964,
      "t1": 29468,
      "t2": 0,
      "t3": 0,
      "t4": 39767,
      "t5": 47170,
      "help": 309,
      "dt": "2026/03/06",
      "dead_t1": 0,
      "dead_t2": 0,
      "dead_t3": 0,
      "dead_t4": 55013,
      "dead_t5": 0
    },
    {
      "id": "132188089",
      "name": "OnE farm 2",
      "max_power": 20958285,
      "power": 20957133,
      "collect": 772479930,
      "dead": 0,
      "kill": 979761,
      "t1": 14108,
      "t2": 0,
      "t3": 0,
      "t4": 97694,
      "t5": 0,
      "help": 237,
      "dt": "2026/03/06",
      "dead_t1": 0,
      "dead_t2": 0,
      "dead_t3": 0,
      "dead_t4": 0,
      "dead_t5": 0
    },
    {
      "id": "70168071",
      "name": "Cranks farm",
      "max_power": 19822430,
      "power": 19822430,
      "collect": 956615381,
      "dead": 0,
      "kill": 0,
      "t1": 0,
      "t2": 0,
      "t3": 0,
      "t4": 0,
      "t5": 0,
      "help": 224,
      "dt": "2026/03/06",
      "dead_t1": 0,
      "dead_t2": 0,
      "dead_t3": 0,
      "dead_t4": 0,
      "dead_t5": 0
    },
    {
      "id": "65838981",
      "name": "Kaido Farm 1",
      "max_power": 27013871,
      "power": 19562688,
      "collect": 333456353,
      "dead": 584666,
      "kill": 693500,
      "t1": 0,
      "t2": 0,
      "t3": 0,
      "t4": 0,
      "t5": 34675,
      "help": 44,
      "dt": "2026/03/06",
      "dead_t1": 0,
      "dead_t2": 0,
      "dead_t3": 0,
      "dead_t4": 0,
      "dead_t5": 0
    },
    {
      "id": "129254749",
      "name": "Tomato07",
      "max_power": 20327053,
      "power": 19000883,
      "collect": 69530326,
      "dead": 337782,
      "kill": 3354600,
      "t1": 0,
      "t2": 0,
      "t3": 0,
      "t4": 56254,
      "t5": 139603,
      "help": 26,
      "dt": "2026/03/06",
      "dead_t1": 4431,
      "dead_t2": 0,
      "dead_t3": 6114,
      "dead_t4": 121559,
      "dead_t5": 0
    },
    {
      "id": "119099074",
      "name": "Naszgul1",
      "max_power": 18594689,
      "power": 17500469,
      "collect": 29962797,
      "dead": 243425,
      "kill": 2480864,
      "t1": 0,
      "t2": 0,
      "t3": 95401,
      "t4": 60596,
      "t5": 74665,
      "help": 23,
      "dt": "2026/03/06",
      "dead_t1": 0,
      "dead_t2": 0,
      "dead_t3": 0,
      "dead_t4": 171611,
      "dead_t5": 0
    },
    {
      "id": "52167966",
      "name": "Governor52167966",
      "max_power": 17440352,
      "power": 17440352,
      "collect": 52518769,
      "dead": 0,
      "kill": 26780,
      "t1": 0,
      "t2": 0,
      "t3": 0,
      "t4": 90,
      "t5": 1294,
      "help": 2,
      "dt": "2026/03/06",
      "dead_t1": 0,
      "dead_t2": 0,
      "dead_t3": 0,
      "dead_t4": 0,
      "dead_t5": 0
    },
    {
      "id": "125253398",
      "name": "Kaido Farm 5",
      "max_power": 17410682,
      "power": 16592290,
      "collect": 325861708,
      "dead": 481611,
      "kill": 506260,
      "t1": 0,
      "t2": 0,
      "t3": 0,
      "t4": 0,
      "t5": 25313,
      "help": 48,
      "dt": "2026/03/06",
      "dead_t1": 0,
      "dead_t2": 0,
      "dead_t3": 0,
      "dead_t4": 0,
      "dead_t5": 0
    },
    {
      "id": "46269954",
      "name": "Governor46269954",
      "max_power": 13891578,
      "power": 11341058,
      "collect": 30,
      "dead": 29766,
      "kill": 160170,
      "t1": 0,
      "t2": 0,
      "t3": 0,
      "t4": 61,
      "t5": 7978,
      "help": 0,
      "dt": "2026/03/06",
      "dead_t1": 0,
      "dead_t2": 0,
      "dead_t3": 0,
      "dead_t4": 0,
      "dead_t5": 0
    },
    {
      "id": "52307236",
      "name": "Governor52307236",
      "max_power": 816617,
      "power": 816617,
      "collect": 0,
      "dead": 0,
      "kill": 0,
      "t1": 0,
      "t2": 0,
      "t3": 0,
      "t4": 0,
      "t5": 0,
      "help": 4,
      "dt": "2026/03/06",
      "dead_t1": 0,
      "dead_t2": 0,
      "dead_t3": 0,
      "dead_t4": 0,
      "dead_t5": 0
    },
    {
      "id": "209433263",
      "name": "Governor209433263",
      "max_power": 42231,
      "power": 42231,
      "collect": 0,
      "dead": 0,
      "kill": 0,
      "t1": 0,
      "t2": 0,
      "t3": 0,
      "t4": 0,
      "t5": 0,
      "help": 0,
      "dt": "2026/03/06",
      "dead_t1": 0,
      "dead_t2": 0,
      "dead_t3": 0,
      "dead_t4": 0,
      "dead_t5": 0
    }
  ]
}