{
  "kingdom": 2029,
  "from_date": "2025-09-08",
  "to_date": "2026-03-06",
  "data": [
    {
      "id": "41425852",
      "name": "BomDong",
      "max_power": 164613930,
      "power": 161166570,
      "collect": 2185224344,
      "dead": 415701,
      "kill": 119407247,
      "t1": 1,
      "t2": 793,
      "t3": 0,
      "t4": 466114,
      "t5": 5737226,
      "help": 8967,
      "dt": "2026/03/06",
      "dead_t1": 0,
      "dead_t2": 0,
      "dead_t3": 0,
      "dead_t4": 0,
      "dead_t5": 415701
    },
    {
      "id": "44713663",
      "name": "Bearsiki亗",
      "max_power": 146998507,
      "power": 146998507,
      "collect": 4920502425,
      "dead": 317699,
      "kill": 220169284,
      "t1": 84960,
      "t2": 1,
      "t3": 0,
      "t4": 1258669,
      "t5": 10378280,
      "help": 8331,
      "dt": "2026/03/06",
      "dead_t1": 1,
      "dead_t2": 0,
      "dead_t3": 0,
      "dead_t4": 0,
      "dead_t5": 317698
    },
    {
      "id": "63133851",
      "name": "yayaやや야야",
      "max_power": 144033657,
      "power": 144033657,
      "collect": 2002462059,
      "dead": 102541,
      "kill": 403517574,
      "t1": 71619,
      "t2": 0,
      "t3": 0,
      "t4": 3283039,
      "t5": 18533643,
      "help": 2148,
      "dt": "2026/03/06",
      "dead_t1": 0,
      "dead_t2": 0,
      "dead_t3": 0,
      "dead_t4": 0,
      "dead_t5": 102541
    },
    {
      "id": "84331908",
      "name": "행복물개",
      "max_power": 137473877,
      "power": 137473877,
      "collect": 3442165994,
      "dead": 163319,
      "kill": 746873067,
      "t1": 280558,
      "t2": 14924,
      "t3": 19722,
      "t4": 7715138,
      "t5": 33477842,
      "help": 7310,
      "dt": "2026/03/06",
      "dead_t1": 0,
      "dead_t2": 0,
      "dead_t3": 0,
      "dead_t4": 0,
      "dead_t5": 163319
    },
    {
      "id": "32089228",
      "name": "소년명수코코의 콧물단속",
      "max_power": 151349401,
      "power": 134546044,
      "collect": 947404246,
      "dead": 1626566,
      "kill": 421094114,
      "t1": 947238,
      "t2": 14647,
      "t3": 310193,
      "t4": 5283022,
      "t5": 18340219,
      "help": 1928,
      "dt": "2026/03/06",
      "dead_t1": 0,
      "dead_t2": 0,
      "dead_t3": 0,
      "dead_t4": 177394,
      "dead_t5": 1424749
    },
    {
      "id": "49825600",
      "name": "울트라캡숑",
      "max_power": 126923808,
      "power": 126271315,
      "collect": 4392901294,
      "dead": 1109522,
      "kill": 798565636,
      "t1": 2707112,
      "t2": 581720,
      "t3": 111041,
      "t4": 13172147,
      "t5": 33234757,
      "help": 30331,
      "dt": "2026/03/06",
      "dead_t1": 395,
      "dead_t2": 0,
      "dead_t3": 0,
      "dead_t4": 0,
      "dead_t5": 700085
    },
    {
      "id": "44204898",
      "name": "마리다",
      "max_power": 125827063,
      "power": 125442562,
      "collect": 4317152906,
      "dead": 476180,
      "kill": 544869663,
      "t1": 7029484,
      "t2": 359781,
      "t3": 115266,
      "t4": 8229988,
      "t5": 22999163,
      "help": 12375,
      "dt": "2026/03/06",
      "dead_t1": 0,
      "dead_t2": 0,
      "dead_t3": 0,
      "dead_t4": 0,
      "dead_t5": 476180
    },
    {
      "id": "33859369",
      "name": "Moonz ᴷˡᴺ",
      "max_power": 126946320,
      "power": 125233328,
      "collect": 1265102562,
      "dead": 421992,
      "kill": 211379760,
      "t1": 249,
      "t2": 0,
      "t3": 0,
      "t4": 1929991,
      "t5": 9603990,
      "help": 5429,
      "dt": "2026/03/06",
      "dead_t1": 0,
      "dead_t2": 0,
      "dead_t3": 0,
      "dead_t4": 414,
      "dead_t5": 421578
    },
    {
      "id": "38064573",
      "name": "고라니의 노쇼단속",
      "max_power": 136388913,
      "power": 124347369,
      "collect": 2655855459,
      "dead": 224369,
      "kill": 511866989,
      "t1": 190294,
      "t2": 5679,
      "t3": 10618,
      "t4": 7146074,
      "t5": 22015718,
      "help": 5168,
      "dt": "2026/03/06",
      "dead_t1": 0,
      "dead_t2": 0,
      "dead_t3": 0,
      "dead_t4": 0,
      "dead_t5": 224369
    },
    {
      "id": "49756516",
      "name": "生맥주한잔",
      "max_power": 124912806,
      "power": 124289346,
      "collect": 1285570200,
      "dead": 1079619,
      "kill": 145038770,
      "t1": 1,
      "t2": 0,
      "t3": 0,
      "t4": 1323267,
      "t5": 6590305,
      "help": 4552,
      "dt": "2026/03/06",
      "dead_t1": 0,
      "dead_t2": 0,
      "dead_t3": 0,
      "dead_t4": 0,
      "dead_t5": 1079619
    },
    {
      "id": "32444461",
      "name": "토닥토닥 왕콜라",
      "max_power": 123080177,
      "power": 123080177,
      "collect": 2750116903,
      "dead": 1591437,
      "kill": 357325545,
      "t1": 18135164,
      "t2": 1,
      "t3": 0,
      "t4": 4065987,
      "t5": 15651932,
      "help": 6838,
      "dt": "2026/03/06",
      "dead_t1": 0,
      "dead_t2": 0,
      "dead_t3": 0,
      "dead_t4": 0,
      "dead_t5": 1591437
    },
    {
      "id": "32396230",
      "name": "네오네오",
      "max_power": 122725484,
      "power": 122725484,
      "collect": 3254918584,
      "dead": 58669,
      "kill": 78036310,
      "t1": 1,
      "t2": 0,
      "t3": 0,
      "t4": 54491,
      "t5": 3874570,
      "help": 6313,
      "dt": "2026/03/06",
      "dead_t1": 0,
      "dead_t2": 0,
      "dead_t3": 0,
      "dead_t4": 0,
      "dead_t5": 58669
    },
    {
      "id": "64657324",
      "name": "onNET",
      "max_power": 124111399,
      "power": 120219719,
      "collect": 4881459847,
      "dead": 853668,
      "kill": 344174245,
      "t1": 52056,
      "t2": 2,
      "t3": 0,
      "t4": 2066461,
      "t5": 16174961,
      "help": 24556,
      "dt": "2026/03/06",
      "dead_t1": 0,
      "dead_t2": 0,
      "dead_t3": 0,
      "dead_t4": 0,
      "dead_t5": 853668
    },
    {
      "id": "44139981",
      "name": "무궁화 꽃이 피었습니다",
      "max_power": 122556075,
      "power": 119687781,
      "collect": 1281766353,
      "dead": 61,
      "kill": 93219208,
      "t1": 190458,
      "t2": 17716,
      "t3": 19286,
      "t4": 932698,
      "t5": 4187078,
      "help": 5145,
      "dt": "2026/03/06",
      "dead_t1": 0,
      "dead_t2": 0,
      "dead_t3": 0,
      "dead_t4": 0,
      "dead_t5": 61
    },
    {
      "id": "72643544",
      "name": "하니차니",
      "max_power": 119118705,
      "power": 118885845,
      "collect": 5689285183,
      "dead": 434522,
      "kill": 579215262,
      "t1": 10845573,
      "t2": 116345,
      "t3": 16282,
      "t4": 3593383,
      "t5": 27040725,
      "help": 6639,
      "dt": "2026/03/06",
      "dead_t1": 0,
      "dead_t2": 0,
      "dead_t3": 0,
      "dead_t4": 0,
      "dead_t5": 434522
    },
    {
      "id": "36254318",
      "name": "잠들어버린듀리시키",
      "max_power": 118289427,
      "power": 118273507,
      "collect": 4770448161,
      "dead": 682789,
      "kill": 567125181,
      "t1": 670255,
      "t2": 42143,
      "t3": 259266,
      "t4": 5054638,
      "t5": 25766170,
      "help": 12990,
      "dt": "2026/03/06",
      "dead_t1": 0,
      "dead_t2": 0,
      "dead_t3": 0,
      "dead_t4": 29328,
      "dead_t5": 653461
    },
    {
      "id": "34159041",
      "name": "이안싼쓰",
      "max_power": 118030513,
      "power": 118026613,
      "collect": 1039480506,
      "dead": 0,
      "kill": 0,
      "t1": 0,
      "t2": 0,
      "t3": 0,
      "t4": 0,
      "t5": 0,
      "help": 760,
      "dt": "2026/03/06",
      "dead_t1": 0,
      "dead_t2": 0,
      "dead_t3": 0,
      "dead_t4": 0,
      "dead_t5": 0
    },
    {
      "id": "53263942",
      "name": "Caesar mori",
      "max_power": 116547802,
      "power": 116547802,
      "collect": 2821681383,
      "dead": 669595,
      "kill": 756601295,
      "t1": 39795,
      "t2": 46353,
      "t3": 126130,
      "t4": 26218499,
      "t5": 24690556,
      "help": 7458,
      "dt": "2026/03/06",
      "dead_t1": 0,
      "dead_t2": 0,
      "dead_t3": 0,
      "dead_t4": 265452,
      "dead_t5": 404143
    },
    {
      "id": "35247450",
      "name": "문  앙",
      "max_power": 116299657,
      "power": 114963336,
      "collect": 1553405470,
      "dead": 100774,
      "kill": 79326159,
      "t1": 1791,
      "t2": 0,
      "t3": 0,
      "t4": 2668750,
      "t5": 2631915,
      "help": 5542,
      "dt": "2026/03/06",
      "dead_t1": 0,
      "dead_t2": 0,
      "dead_t3": 0,
      "dead_t4": 0,
      "dead_t5": 18560
    },
    {
      "id": "33797532",
      "name": "에바 ᴷˡᴺ",
      "max_power": 126267126,
      "power": 114599335,
      "collect": 959278937,
      "dead": 568124,
      "kill": 83518810,
      "t1": 0,
      "t2": 0,
      "t3": 0,
      "t4": 867147,
      "t5": 3742367,
      "help": 12101,
      "dt": "2026/03/06",
      "dead_t1": 0,
      "dead_t2": 0,
      "dead_t3": 0,
      "dead_t4": 0,
      "dead_t5": 568130
    },
    {
      "id": "33108418",
      "name": "ˢᵒʸ 소년명수 코코",
      "max_power": 113504304,
      "power": 113503744,
      "collect": 564469048,
      "dead": 0,
      "kill": 1952680,
      "t1": 0,
      "t2": 0,
      "t3": 0,
      "t4": 8142,
      "t5": 93563,
      "help": 177,
      "dt": "2026/03/06",
      "dead_t1": 0,
      "dead_t2": 0,
      "dead_t3": 0,
      "dead_t4": 0,
      "dead_t5": 0
    },
    {
      "id": "32575090",
      "name": "크롬하츠",
      "max_power": 126928955,
      "power": 109946670,
      "collect": 648511150,
      "dead": 1493480,
      "kill": 423074642,
      "t1": 114681,
      "t2": 651,
      "t3": 11,
      "t4": 1359430,
      "t5": 20472803,
      "help": 1390,
      "dt": "2026/03/06",
      "dead_t1": 0,
      "dead_t2": 0,
      "dead_t3": 0,
      "dead_t4": 15539,
      "dead_t5": 1477941
    },
    {
      "id": "31781266",
      "name": "티리엘l",
      "max_power": 110294680,
      "power": 109743630,
      "collect": 1041042024,
      "dead": 9665,
      "kill": 236853278,
      "t1": 410,
      "t2": 143,
      "t3": 0,
      "t4": 1261717,
      "t5": 11211787,
      "help": 2460,
      "dt": "2026/03/06",
      "dead_t1": 0,
      "dead_t2": 0,
      "dead_t3": 0,
      "dead_t4": 0,
      "dead_t5": 9665
    },
    {
      "id": "98389951",
      "name": "ᴬᴱ Icykof",
      "max_power": 113769706,
      "power": 108983981,
      "collect": 1671272458,
      "dead": 1176048,
      "kill": 15197800,
      "t1": 1,
      "t2": 0,
      "t3": 0,
      "t4": 208440,
      "t5": 655670,
      "help": 2273,
      "dt": "2026/03/06",
      "dead_t1": 157244,
      "dead_t2": 668205,
      "dead_t3": 184724,
      "dead_t4": 128607,
      "dead_t5": 37268
    },
    {
      "id": "32728604",
      "name": "丶장각丶",
      "max_power": 117976644,
      "power": 97700515,
      "collect": 1649505432,
      "dead": 49402,
      "kill": 82770927,
      "t1": 112737,
      "t2": 71900,
      "t3": 0,
      "t4": 1857794,
      "t5": 3201332,
      "help": 2001,
      "dt": "2026/03/06",
      "dead_t1": 0,
      "dead_t2": 0,
      "dead_t3": 0,
      "dead_t4": 16686,
      "dead_t5": 32716
    },
    {
      "id": "37761432",
      "name": "바쁜녀석들",
      "max_power": 115109120,
      "power": 97147697,
      "collect": 1665129033,
      "dead": 926221,
      "kill": 260393049,
      "t1": 48556,
      "t2": 24810,
      "t3": 92,
      "t4": 1526821,
      "t5": 12253257,
      "help": 5759,
      "dt": "2026/03/06",
      "dead_t1": 0,
      "dead_t2": 0,
      "dead_t3": 0,
      "dead_t4": 120,
      "dead_t5": 926101
    },
    {
      "id": "32430574",
      "name": "엮은이는아는데요김경식씨",
      "max_power": 87802347,
      "power": 87802347,
      "collect": 230591588,
      "dead": 0,
      "kill": 0,
      "t1": 0,
      "t2": 0,
      "t3": 0,
      "t4": 0,
      "t5": 0,
      "help": 92,
      "dt": "2026/03/06",
      "dead_t1": 0,
      "dead_t2": 0,
      "dead_t3": 0,
      "dead_t4": 0,
      "dead_t5": 0
    },
    {
      "id": "54771664",
      "name": "쭌ɞ",
      "max_power": 99329768,
      "power": 86676343,
      "collect": 3976151673,
      "dead": 470046,
      "kill": 78160231,
      "t1": 44,
      "t2": 102,
      "t3": 82,
      "t4": 524791,
      "t5": 3645589,
      "help": 3335,
      "dt": "2026/03/06",
      "dead_t1": 0,
      "dead_t2": 0,
      "dead_t3": 0,
      "dead_t4": 352698,
      "dead_t5": 117348
    },
    {
      "id": "99952998",
      "name": "Astroboy28",
      "max_power": 86087771,
      "power": 86022195,
      "collect": 1932775676,
      "dead": 160920,
      "kill": 22815050,
      "t1": 52,
      "t2": 70,
      "t3": 0,
      "t4": 342668,
      "t5": 969411,
      "help": 4021,
      "dt": "2026/03/06",
      "dead_t1": 0,
      "dead_t2": 0,
      "dead_t3": 0,
      "dead_t4": 160920,
      "dead_t5": 0
    },
    {
      "id": "32503735",
      "name": "형이 왜 거기서 나와",
      "max_power": 79387790,
      "power": 79387790,
      "collect": 230966493,
      "dead": 0,
      "kill": 1797140,
      "t1": 0,
      "t2": 0,
      "t3": 0,
      "t4": 0,
      "t5": 89857,
      "help": 65,
      "dt": "2026/03/06",
      "dead_t1": 0,
      "dead_t2": 0,
      "dead_t3": 0,
      "dead_t4": 0,
      "dead_t5": 0
    },
    {
      "id": "49170011",
      "name": "변신의 용사 여기 잠들다zz",
      "max_power": 76220289,
      "power": 76220289,
      "collect": 657954208,
      "dead": 0,
      "kill": 0,
      "t1": 0,
      "t2": 0,
      "t3": 0,
      "t4": 0,
      "t5": 0,
      "help": 127,
      "dt": "2026/03/06",
      "dead_t1": 0,
      "dead_t2": 0,
      "dead_t3": 0,
      "dead_t4": 0,
      "dead_t5": 0
    },
    {
      "id": "33573826",
      "name": "바쁜녀석",
      "max_power": 86057203,
      "power": 75743031,
      "collect": 421515980,
      "dead": 0,
      "kill": 0,
      "t1": 0,
      "t2": 0,
      "t3": 0,
      "t4": 0,
      "t5": 0,
      "help": 162,
      "dt": "2026/03/06",
      "dead_t1": 0,
      "dead_t2": 0,
      "dead_t3": 0,
      "dead_t4": 0,
      "dead_t5": 0
    },
    {
      "id": "73152066",
      "name": "総督73152066",
      "max_power": 68575724,
      "power": 68514904,
      "collect": 1117179959,
      "dead": 97945,
      "kill": 1564080,
      "t1": 0,
      "t2": 0,
      "t3": 0,
      "t4": 0,
      "t5": 78204,
      "help": 61,
      "dt": "2026/03/06",
      "dead_t1": 0,
      "dead_t2": 0,
      "dead_t3": 0,
      "dead_t4": 0,
      "dead_t5": 0
    },
    {
      "id": "37776493",
      "name": "onNET1",
      "max_power": 60612820,
      "power": 59517952,
      "collect": 1573898024,
      "dead": 0,
      "kill": 0,
      "t1": 0,
      "t2": 0,
      "t3": 0,
      "t4": 0,
      "t5": 0,
      "help": 1541,
      "dt": "2026/03/06",
      "dead_t1": 0,
      "dead_t2": 0,
      "dead_t3": 0,
      "dead_t4": 0,
      "dead_t5": 0
    },
    {
      "id": "66796010",
      "name": "네오네오네오",
      "max_power": 59665704,
      "power": 52580489,
      "collect": 865590403,
      "dead": 0,
      "kill": 0,
      "t1": 0,
      "t2": 0,
      "t3": 0,
      "t4": 0,
      "t5": 0,
      "help": 170,
      "dt": "2026/03/06",
      "dead_t1": 0,
      "dead_t2": 0,
      "dead_t3": 0,
      "dead_t4": 0,
      "dead_t5": 0
    },
    {
      "id": "85173878",
      "name": "무궁화 1호",
      "max_power": 49702678,
      "power": 45733522,
      "collect": 854771804,
      "dead": 2743309,
      "kill": 113413616,
      "t1": 240010,
      "t2": 48076,
      "t3": 153,
      "t4": 1969887,
      "t5": 4678499,
      "help": 1223,
      "dt": "2026/03/06",
      "dead_t1": 0,
      "dead_t2": 0,
      "dead_t3": 0,
      "dead_t4": 2743309,
      "dead_t5": 0
    },
    {
      "id": "35265089",
      "name": "샤르카 ᴷˡᴺ",
      "max_power": 44200215,
      "power": 43202809,
      "collect": 369059707,
      "dead": 0,
      "kill": 452460,
      "t1": 0,
      "t2": 0,
      "t3": 0,
      "t4": 0,
      "t5": 22623,
      "help": 290,
      "dt": "2026/03/06",
      "dead_t1": 0,
      "dead_t2": 0,
      "dead_t3": 0,
      "dead_t4": 0,
      "dead_t5": 0
    },
    {
      "id": "47733356",
      "name": "onNET2",
      "max_power": 41797635,
      "power": 41795067,
      "collect": 1465842399,
      "dead": 0,
      "kill": 0,
      "t1": 0,
      "t2": 0,
      "t3": 0,
      "t4": 0,
      "t5": 0,
      "help": 1383,
      "dt": "2026/03/06",
      "dead_t1": 0,
      "dead_t2": 0,
      "dead_t3": 0,
      "dead_t4": 0,
      "dead_t5": 0
    },
    {
      "id": "34720238",
      "name": "웃지마 민병관",
      "max_power": 47681134,
      "power": 41315358,
      "collect": 292082437,
      "dead": 0,
      "kill": 0,
      "t1": 0,
      "t2": 0,
      "t3": 0,
      "t4": 0,
      "t5": 0,
      "help": 28,
      "dt": "2026/03/06",
      "dead_t1": 0,
      "dead_t2": 0,
      "dead_t3": 0,
      "dead_t4": 0,
      "dead_t5": 0
    },
    {
      "id": "33667584",
      "name": "나십잡쓰야",
      "max_power": 43312103,
      "power": 41266354,
      "collect": 422594335,
      "dead": 518090,
      "kill": 635630,
      "t1": 0,
      "t2": 0,
      "t3": 0,
      "t4": 2313,
      "t5": 30625,
      "help": 51,
      "dt": "2026/03/06",
      "dead_t1": 0,
      "dead_t2": 0,
      "dead_t3": 0,
      "dead_t4": 0,
      "dead_t5": 0
    },
    {
      "id": "105479368",
      "name": "무궁화 2호",
      "max_power": 40606923,
      "power": 40605623,
      "collect": 536506688,
      "dead": 0,
      "kill": 179260,
      "t1": 0,
      "t2": 0,
      "t3": 0,
      "t4": 0,
      "t5": 8963,
      "help": 326,
      "dt": "2026/03/06",
      "dead_t1": 0,
      "dead_t2": 0,
      "dead_t3": 0,
      "dead_t4": 0,
      "dead_t5": 0
    },
    {
      "id": "90118650",
      "name": "하니차니 22",
      "max_power": 45593834,
      "power": 40067129,
      "collect": 5654253485,
      "dead": 719625,
      "kill": 11592209,
      "t1": 44,
      "t2": 20,
      "t3": 10,
      "t4": 309774,
      "t5": 424719,
      "help": 2280,
      "dt": "2026/03/06",
      "dead_t1": 0,
      "dead_t2": 0,
      "dead_t3": 0,
      "dead_t4": 719625,
      "dead_t5": 0
    },
    {
      "id": "98828826",
      "name": "icyfarms",
      "max_power": 39731593,
      "power": 39523921,
      "collect": 19585744,
      "dead": 0,
      "kill": 3402825,
      "t1": 207244,
      "t2": 668205,
      "t3": 184724,
      "t4": 128607,
      "t5": 0,
      "help": 70,
      "dt": "2026/03/06",
      "dead_t1": 0,
      "dead_t2": 0,
      "dead_t3": 0,
      "dead_t4": 0,
      "dead_t5": 0
    },
    {
      "id": "86726445",
      "name": "하니차니3",
      "max_power": 38950756,
      "power": 38940300,
      "collect": 5570982317,
      "dead": 1599349,
      "kill": 35076041,
      "t1": 19816,
      "t2": 18233,
      "t3": 15963,
      "t4": 768812,
      "t5": 1364182,
      "help": 2711,
      "dt": "2026/03/06",
      "dead_t1": 0,
      "dead_t2": 0,
      "dead_t3": 0,
      "dead_t4": 1599349,
      "dead_t5": 0
    },
    {
      "id": "96016657",
      "name": "물개FARM 해달",
      "max_power": 39339128,
      "power": 37098012,
      "collect": 5298028123,
      "dead": 2676121,
      "kill": 25175352,
      "t1": 89,
      "t2": 340,
      "t3": 76,
      "t4": 658691,
      "t5": 929372,
      "help": 1375,
      "dt": "2026/03/06",
      "dead_t1": 0,
      "dead_t2": 0,
      "dead_t3": 0,
      "dead_t4": 2676121,
      "dead_t5": 0
    },
    {
      "id": "89467860",
      "name": "물개FARM  바다코끼리",
      "max_power": 38747683,
      "power": 36474183,
      "collect": 5300482091,
      "dead": 2352589,
      "kill": 18800145,
      "t1": 84,
      "t2": 190,
      "t3": 62,
      "t4": 568636,
      "t5": 655657,
      "help": 1496,
      "dt": "2026/03/06",
      "dead_t1": 0,
      "dead_t2": 0,
      "dead_t3": 0,
      "dead_t4": 2352589,
      "dead_t5": 0
    },
    {
      "id": "90430820",
      "name": "물개FARM 듀공",
      "max_power": 38359402,
      "power": 36345882,
      "collect": 5357217688,
      "dead": 2552230,
      "kill": 23247921,
      "t1": 47,
      "t2": 47,
      "t3": 92,
      "t4": 698673,
      "t5": 813036,
      "help": 1336,
      "dt": "2026/03/06",
      "dead_t1": 0,
      "dead_t2": 0,
      "dead_t3": 0,
      "dead_t4": 2552230,
      "dead_t5": 0
    },
    {
      "id": "36525711",
      "name": "문 앙 sub1",
      "max_power": 40830846,
      "power": 36282565,
      "collect": 393484976,
      "dead": 0,
      "kill": 0,
      "t1": 0,
      "t2": 0,
      "t3": 0,
      "t4": 0,
      "t5": 0,
      "help": 138,
      "dt": "2026/03/06",
      "dead_t1": 0,
      "dead_t2": 0,
      "dead_t3": 0,
      "dead_t4": 0,
      "dead_t5": 0
    },
    {
      "id": "96016379",
      "name": "물개FARM 수달",
      "max_power": 37514118,
      "power": 35233966,
      "collect": 5373039342,
      "dead": 2719506,
      "kill": 20599612,
      "t1": 32,
      "t2": 96,
      "t3": 16,
      "t4": 550569,
      "t5": 754683,
      "help": 1306,
      "dt": "2026/03/06",
      "dead_t1": 0,
      "dead_t2": 0,
      "dead_t3": 0,
      "dead_t4": 2719882,
      "dead_t5": 0
    },
    {
      "id": "67935544",
      "name": "Mori Soldier1",
      "max_power": 54465718,
      "power": 34662635,
      "collect": 1996909704,
      "dead": 8318881,
      "kill": 34635072,
      "t1": 35739,
      "t2": 15498,
      "t3": 167,
      "t4": 1007720,
      "t5": 1225953,
      "help": 615,
      "dt": "2026/03/06",
      "dead_t1": 33,
      "dead_t2": 0,
      "dead_t3": 0,
      "dead_t4": 8323937,
      "dead_t5": 0
    },
    {
      "id": "65062366",
      "name": "쭌 옥수수",
      "max_power": 39599627,
      "power": 34429885,
      "collect": 1010493954,
      "dead": 0,
      "kill": 0,
      "t1": 0,
      "t2": 0,
      "t3": 0,
      "t4": 0,
      "t5": 0,
      "help": 147,
      "dt": "2026/03/06",
      "dead_t1": 0,
      "dead_t2": 0,
      "dead_t3": 0,
      "dead_t4": 0,
      "dead_t5": 0
    },
    {
      "id": "63834059",
      "name": "쭌 통나무",
      "max_power": 36554235,
      "power": 33920974,
      "collect": 1002982280,
      "dead": 0,
      "kill": 0,
      "t1": 0,
      "t2": 0,
      "t3": 0,
      "t4": 0,
      "t5": 0,
      "help": 82,
      "dt": "2026/03/06",
      "dead_t1": 0,
      "dead_t2": 0,
      "dead_t3": 0,
      "dead_t4": 0,
      "dead_t5": 0
    },
    {
      "id": "36251696",
      "name": "봄도 F1",
      "max_power": 37011707,
      "power": 33601727,
      "collect": 570728316,
      "dead": 2297418,
      "kill": 67763517,
      "t1": 107955,
      "t2": 46763,
      "t3": 23685,
      "t4": 1135910,
      "t5": 2809728,
      "help": 540,
      "dt": "2026/03/06",
      "dead_t1": 1,
      "dead_t2": 0,
      "dead_t3": 0,
      "dead_t4": 2297417,
      "dead_t5": 0
    },
    {
      "id": "36785679",
      "name": "바쁜녀석3",
      "max_power": 33501440,
      "power": 32523876,
      "collect": 730901211,
      "dead": 2329265,
      "kill": 22382995,
      "t1": 95,
      "t2": 3521,
      "t3": 116,
      "t4": 624439,
      "t5": 806554,
      "help": 308,
      "dt": "2026/03/06",
      "dead_t1": 0,
      "dead_t2": 0,
      "dead_t3": 0,
      "dead_t4": 2329265,
      "dead_t5": 0
    },
    {
      "id": "69833239",
      "name": "onNET3",
      "max_power": 41449863,
      "power": 31188820,
      "collect": 3938565349,
      "dead": 2921921,
      "kill": 50679324,
      "t1": 118431,
      "t2": 58409,
      "t3": 38640,
      "t4": 832078,
      "t5": 2103174,
      "help": 2557,
      "dt": "2026/03/06",
      "dead_t1": 0,
      "dead_t2": 0,
      "dead_t3": 0,
      "dead_t4": 2922570,
      "dead_t5": 0
    },
    {
      "id": "151148093",
      "name": "물개FARM 오리너구리",
      "max_power": 33189545,
      "power": 31081445,
      "collect": 5919991502,
      "dead": 602000,
      "kill": 15764,
      "t1": 222,
      "t2": 355,
      "t3": 0,
      "t4": 275,
      "t5": 613,
      "help": 487,
      "dt": "2026/03/06",
      "dead_t1": 0,
      "dead_t2": 0,
      "dead_t3": 0,
      "dead_t4": 0,
      "dead_t5": 0
    },
    {
      "id": "131395553",
      "name": "Mori Soldier3",
      "max_power": 43922797,
      "power": 31062445,
      "collect": 1003866421,
      "dead": 3851841,
      "kill": 872480,
      "t1": 0,
      "t2": 0,
      "t3": 0,
      "t4": 0,
      "t5": 43624,
      "help": 147,
      "dt": "2026/03/06",
      "dead_t1": 0,
      "dead_t2": 0,
      "dead_t3": 7997,
      "dead_t4": 3843844,
      "dead_t5": 0
    },
    {
      "id": "63365979",
      "name": "바쁜녀석4",
      "max_power": 30987159,
      "power": 30987159,
      "collect": 961258954,
      "dead": 0,
      "kill": 0,
      "t1": 0,
      "t2": 0,
      "t3": 0,
      "t4": 0,
      "t5": 0,
      "help": 192,
      "dt": "2026/03/06",
      "dead_t1": 0,
      "dead_t2": 0,
      "dead_t3": 0,
      "dead_t4": 0,
      "dead_t5": 0
    },
    {
      "id": "34861343",
      "name": "LV35 PONGSHEW",
      "max_power": 41097640,
      "power": 30839829,
      "collect": 7092750,
      "dead": 0,
      "kill": 0,
      "t1": 0,
      "t2": 0,
      "t3": 0,
      "t4": 0,
      "t5": 0,
      "help": 3,
      "dt": "2026/03/06",
      "dead_t1": 0,
      "dead_t2": 0,
      "dead_t3": 0,
      "dead_t4": 0,
      "dead_t5": 0
    },
    {
      "id": "115556417",
      "name": "무궁화 3호",
      "max_power": 30784463,
      "power": 30781819,
      "collect": 516794679,
      "dead": 0,
      "kill": 157140,
      "t1": 0,
      "t2": 0,
      "t3": 0,
      "t4": 0,
      "t5": 7857,
      "help": 167,
      "dt": "2026/03/06",
      "dead_t1": 0,
      "dead_t2": 0,
      "dead_t3": 0,
      "dead_t4": 0,
      "dead_t5": 0
    },
    {
      "id": "110593809",
      "name": "Mori Soldier2",
      "max_power": 42453867,
      "power": 30750159,
      "collect": 1068181645,
      "dead": 3666544,
      "kill": 852560,
      "t1": 0,
      "t2": 0,
      "t3": 0,
      "t4": 0,
      "t5": 42628,
      "help": 141,
      "dt": "2026/03/06",
      "dead_t1": 0,
      "dead_t2": 0,
      "dead_t3": 0,
      "dead_t4": 3302359,
      "dead_t5": 0
    },
    {
      "id": "150144521",
      "name": "Mori Soldier4",
      "max_power": 33807366,
      "power": 30739613,
      "collect": 1767718100,
      "dead": 1471292,
      "kill": 4199800,
      "t1": 18502,
      "t2": 7030,
      "t3": 0,
      "t4": 113282,
      "t5": 152461,
      "help": 867,
      "dt": "2026/03/06",
      "dead_t1": 7256,
      "dead_t2": 0,
      "dead_t3": 13449,
      "dead_t4": 1415570,
      "dead_t5": 0
    },
    {
      "id": "36330986",
      "name": "바쁜녀석5",
      "max_power": 30763151,
      "power": 30730760,
      "collect": 915491682,
      "dead": 965218,
      "kill": 7297866,
      "t1": 10,
      "t2": 87,
      "t3": 0,
      "t4": 229253,
      "t5": 250258,
      "help": 301,
      "dt": "2026/03/06",
      "dead_t1": 0,
      "dead_t2": 0,
      "dead_t3": 0,
      "dead_t4": 965218,
      "dead_t5": 0
    },
    {
      "id": "156124547",
      "name": "Mori Soldier5",
      "max_power": 37731634,
      "power": 30516964,
      "collect": 1785037537,
      "dead": 2465292,
      "kill": 2583180,
      "t1": 0,
      "t2": 0,
      "t3": 0,
      "t4": 0,
      "t5": 129159,
      "help": 560,
      "dt": "2026/03/06",
      "dead_t1": 12008,
      "dead_t2": 46020,
      "dead_t3": 104684,
      "dead_t4": 2302580,
      "dead_t5": 0
    },
    {
      "id": "53122370",
      "name": "울트라파국",
      "max_power": 37078963,
      "power": 30242547,
      "collect": 3048911265,
      "dead": 1284973,
      "kill": 11731674,
      "t1": 2457898,
      "t2": 171067,
      "t3": 75,
      "t4": 265588,
      "t5": 412089,
      "help": 1489,
      "dt": "2026/03/06",
      "dead_t1": 0,
      "dead_t2": 0,
      "dead_t3": 0,
      "dead_t4": 1284973,
      "dead_t5": 0
    },
    {
      "id": "41381855",
      "name": "코코팜 복숭아",
      "max_power": 31673754,
      "power": 30128581,
      "collect": 705308864,
      "dead": 1257956,
      "kill": 25403451,
      "t1": 9795,
      "t2": 4416,
      "t3": 0,
      "t4": 527862,
      "t5": 1005702,
      "help": 206,
      "dt": "2026/03/06",
      "dead_t1": 0,
      "dead_t2": 0,
      "dead_t3": 0,
      "dead_t4": 1257956,
      "dead_t5": 0
    },
    {
      "id": "151147437",
      "name": "물개FARM 비버",
      "max_power": 34389662,
      "power": 30122562,
      "collect": 5922612693,
      "dead": 1208000,
      "kill": 99198,
      "t1": 1920,
      "t2": 2267,
      "t3": 0,
      "t4": 1626,
      "t5": 3901,
      "help": 500,
      "dt": "2026/03/06",
      "dead_t1": 0,
      "dead_t2": 0,
      "dead_t3": 0,
      "dead_t4": 0,
      "dead_t5": 0
    },
    {
      "id": "62619688",
      "name": "테라한잔",
      "max_power": 35249181,
      "power": 29992995,
      "collect": 611816211,
      "dead": 391713,
      "kill": 6726698,
      "t1": 78,
      "t2": 63,
      "t3": 129,
      "t4": 183874,
      "t5": 244365,
      "help": 614,
      "dt": "2026/03/06",
      "dead_t1": 0,
      "dead_t2": 0,
      "dead_t3": 0,
      "dead_t4": 391713,
      "dead_t5": 0
    },
    {
      "id": "64481502",
      "name": "yayaやや1",
      "max_power": 39083779,
      "power": 29986471,
      "collect": 933079340,
      "dead": 2182891,
      "kill": 53736792,
      "t1": 33650,
      "t2": 9130,
      "t3": 478,
      "t4": 1205783,
      "t5": 2082603,
      "help": 457,
      "dt": "2026/03/06",
      "dead_t1": 0,
      "dead_t2": 0,
      "dead_t3": 0,
      "dead_t4": 2182891,
      "dead_t5": 0
    },
    {
      "id": "37069113",
      "name": "히트다 히트",
      "max_power": 29946260,
      "power": 29946260,
      "collect": 663494302,
      "dead": 0,
      "kill": 0,
      "t1": 0,
      "t2": 0,
      "t3": 0,
      "t4": 0,
      "t5": 0,
      "help": 42,
      "dt": "2026/03/06",
      "dead_t1": 0,
      "dead_t2": 0,
      "dead_t3": 0,
      "dead_t4": 0,
      "dead_t5": 0
    },
    {
      "id": "36806231",
      "name": "아니아닌데",
      "max_power": 29938423,
      "power": 29938423,
      "collect": 479174331,
      "dead": 0,
      "kill": 0,
      "t1": 0,
      "t2": 0,
      "t3": 0,
      "t4": 0,
      "t5": 0,
      "help": 39,
      "dt": "2026/03/06",
      "dead_t1": 0,
      "dead_t2": 0,
      "dead_t3": 0,
      "dead_t4": 0,
      "dead_t5": 0
    },
    {
      "id": "54947959",
      "name": "파국한잔",
      "max_power": 35509424,
      "power": 29811160,
      "collect": 627335195,
      "dead": 390349,
      "kill": 7580078,
      "t1": 44,
      "t2": 24,
      "t3": 153,
      "t4": 197595,
      "t5": 280173,
      "help": 635,
      "dt": "2026/03/06",
      "dead_t1": 0,
      "dead_t2": 0,
      "dead_t3": 0,
      "dead_t4": 390349,
      "dead_t5": 0
    },
    {
      "id": "136590514",
      "name": "onNET4",
      "max_power": 35927377,
      "power": 29803244,
      "collect": 3893697825,
      "dead": 1828240,
      "kill": 27494498,
      "t1": 49067,
      "t2": 9077,
      "t3": 0,
      "t4": 653855,
      "t5": 1046399,
      "help": 2324,
      "dt": "2026/03/06",
      "dead_t1": 170,
      "dead_t2": 0,
      "dead_t3": 0,
      "dead_t4": 1828070,
      "dead_t5": 0
    },
    {
      "id": "38246798",
      "name": "티리엘 F1",
      "max_power": 41763863,
      "power": 29742223,
      "collect": 454148223,
      "dead": 0,
      "kill": 0,
      "t1": 0,
      "t2": 0,
      "t3": 0,
      "t4": 0,
      "t5": 0,
      "help": 88,
      "dt": "2026/03/06",
      "dead_t1": 0,
      "dead_t2": 0,
      "dead_t3": 0,
      "dead_t4": 0,
      "dead_t5": 0
    },
    {
      "id": "42621334",
      "name": "앞산고라니",
      "max_power": 32214079,
      "power": 29467125,
      "collect": 790759208,
      "dead": 1534329,
      "kill": 25159153,
      "t1": 5,
      "t2": 189,
      "t3": 146,
      "t4": 545911,
      "t5": 984954,
      "help": 278,
      "dt": "2026/03/06",
      "dead_t1": 0,
      "dead_t2": 0,
      "dead_t3": 0,
      "dead_t4": 1534329,
      "dead_t5": 0
    },
    {
      "id": "97658839",
      "name": "ESSE Farm2",
      "max_power": 35809441,
      "power": 29134066,
      "collect": 273857986,
      "dead": 0,
      "kill": 0,
      "t1": 0,
      "t2": 0,
      "t3": 0,
      "t4": 0,
      "t5": 0,
      "help": 69,
      "dt": "2026/03/06",
      "dead_t1": 0,
      "dead_t2": 0,
      "dead_t3": 0,
      "dead_t4": 0,
      "dead_t5": 0
    },
    {
      "id": "159097336",
      "name": "백마탄 노꼬",
      "max_power": 30086872,
      "power": 29023393,
      "collect": 350980380,
      "dead": 750232,
      "kill": 885120,
      "t1": 0,
      "t2": 0,
      "t3": 0,
      "t4": 0,
      "t5": 44256,
      "help": 65,
      "dt": "2026/03/06",
      "dead_t1": 0,
      "dead_t2": 0,
      "dead_t3": 0,
      "dead_t4": 0,
      "dead_t5": 0
    },
    {
      "id": "65292287",
      "name": "쭌 돌",
      "max_power": 37120978,
      "power": 28791469,
      "collect": 2546669699,
      "dead": 165437,
      "kill": 6431170,
      "t1": 17009,
      "t2": 344,
      "t3": 0,
      "t4": 81212,
      "t5": 280748,
      "help": 611,
      "dt": "2026/03/06",
      "dead_t1": 0,
      "dead_t2": 0,
      "dead_t3": 0,
      "dead_t4": 165437,
      "dead_t5": 0
    },
    {
      "id": "101909818",
      "name": "onNET5",
      "max_power": 33085391,
      "power": 28733667,
      "collect": 3325199710,
      "dead": 0,
      "kill": 1220,
      "t1": 0,
      "t2": 0,
      "t3": 0,
      "t4": 0,
      "t5": 61,
      "help": 814,
      "dt": "2026/03/06",
      "dead_t1": 0,
      "dead_t2": 0,
      "dead_t3": 0,
      "dead_t4": 0,
      "dead_t5": 0
    },
    {
      "id": "80187483",
      "name": "쭌 금",
      "max_power": 37339907,
      "power": 28624268,
      "collect": 2626110659,
      "dead": 0,
      "kill": 0,
      "t1": 0,
      "t2": 0,
      "t3": 0,
      "t4": 0,
      "t5": 0,
      "help": 119,
      "dt": "2026/03/06",
      "dead_t1": 0,
      "dead_t2": 0,
      "dead_t3": 0,
      "dead_t4": 0,
      "dead_t5": 0
    },
    {
      "id": "45528309",
      "name": "규1캣",
      "max_power": 39724441,
      "power": 28408809,
      "collect": 2617251707,
      "dead": 2956808,
      "kill": 630424,
      "t1": 2019,
      "t2": 0,
      "t3": 0,
      "t4": 15226,
      "t5": 23888,
      "help": 236,
      "dt": "2026/03/06",
      "dead_t1": 0,
      "dead_t2": 0,
      "dead_t3": 0,
      "dead_t4": 2956808,
      "dead_t5": 0
    },
    {
      "id": "157424811",
      "name": "onNET6",
      "max_power": 31145335,
      "power": 28269978,
      "collect": 3115043565,
      "dead": 0,
      "kill": 900,
      "t1": 0,
      "t2": 0,
      "t3": 0,
      "t4": 0,
      "t5": 45,
      "help": 527,
      "dt": "2026/03/06",
      "dead_t1": 0,
      "dead_t2": 0,
      "dead_t3": 0,
      "dead_t4": 0,
      "dead_t5": 0
    },
    {
      "id": "41600401",
      "name": "봄도 F2",
      "max_power": 30401898,
      "power": 28061870,
      "collect": 313222157,
      "dead": 0,
      "kill": 0,
      "t1": 0,
      "t2": 0,
      "t3": 0,
      "t4": 0,
      "t5": 0,
      "help": 122,
      "dt": "2026/03/06",
      "dead_t1": 0,
      "dead_t2": 0,
      "dead_t3": 0,
      "dead_t4": 0,
      "dead_t5": 0
    },
    {
      "id": "77883692",
      "name": "코코팜 화이트",
      "max_power": 27987975,
      "power": 27987975,
      "collect": 544750466,
      "dead": 52610,
      "kill": 950106,
      "t1": 0,
      "t2": 8,
      "t3": 110,
      "t4": 33025,
      "t5": 30970,
      "help": 112,
      "dt": "2026/03/06",
      "dead_t1": 0,
      "dead_t2": 0,
      "dead_t3": 0,
      "dead_t4": 52610,
      "dead_t5": 0
    },
    {
      "id": "47198560",
      "name": "Yes I Can 코코",
      "max_power": 27878272,
      "power": 27878272,
      "collect": 473550194,
      "dead": 0,
      "kill": 0,
      "t1": 0,
      "t2": 0,
      "t3": 0,
      "t4": 0,
      "t5": 0,
      "help": 110,
      "dt": "2026/03/06",
      "dead_t1": 0,
      "dead_t2": 0,
      "dead_t3": 0,
      "dead_t4": 0,
      "dead_t5": 0
    },
    {
      "id": "73154773",
      "name": "Alphatron124",
      "max_power": 27499747,
      "power": 27499747,
      "collect": 977607223,
      "dead": 0,
      "kill": 0,
      "t1": 0,
      "t2": 0,
      "t3": 0,
      "t4": 0,
      "t5": 0,
      "help": 14,
      "dt": "2026/03/06",
      "dead_t1": 0,
      "dead_t2": 0,
      "dead_t3": 0,
      "dead_t4": 0,
      "dead_t5": 0
    },
    {
      "id": "45668891",
      "name": "LV34 PONGSHEW",
      "max_power": 35802742,
      "power": 27429198,
      "collect": 89370891,
      "dead": 0,
      "kill": 0,
      "t1": 0,
      "t2": 0,
      "t3": 0,
      "t4": 0,
      "t5": 0,
      "help": 8,
      "dt": "2026/03/06",
      "dead_t1": 0,
      "dead_t2": 0,
      "dead_t3": 0,
      "dead_t4": 0,
      "dead_t5": 0
    },
    {
      "id": "39773414",
      "name": "코코 쌀쌀금금",
      "max_power": 26612736,
      "power": 26612736,
      "collect": 368238120,
      "dead": 0,
      "kill": 0,
      "t1": 0,
      "t2": 0,
      "t3": 0,
      "t4": 0,
      "t5": 0,
      "help": 67,
      "dt": "2026/03/06",
      "dead_t1": 0,
      "dead_t2": 0,
      "dead_t3": 0,
      "dead_t4": 0,
      "dead_t5": 0
    },
    {
      "id": "39319496",
      "name": "문 앙 sub2",
      "max_power": 28111968,
      "power": 26574206,
      "collect": 626605593,
      "dead": 0,
      "kill": 0,
      "t1": 0,
      "t2": 0,
      "t3": 0,
      "t4": 0,
      "t5": 0,
      "help": 223,
      "dt": "2026/03/06",
      "dead_t1": 0,
      "dead_t2": 0,
      "dead_t3": 0,
      "dead_t4": 0,
      "dead_t5": 0
    },
    {
      "id": "37362304",
      "name": "마리우스 ᴷˡᴺ",
      "max_power": 26637151,
      "power": 26513484,
      "collect": 47008033,
      "dead": 0,
      "kill": 0,
      "t1": 0,
      "t2": 0,
      "t3": 0,
      "t4": 0,
      "t5": 0,
      "help": 13,
      "dt": "2026/03/06",
      "dead_t1": 0,
      "dead_t2": 0,
      "dead_t3": 0,
      "dead_t4": 0,
      "dead_t5": 0
    },
    {
      "id": "56338298",
      "name": "Bear k farm",
      "max_power": 30740317,
      "power": 26225899,
      "collect": 4564061544,
      "dead": 0,
      "kill": 0,
      "t1": 0,
      "t2": 0,
      "t3": 0,
      "t4": 0,
      "t5": 0,
      "help": 88,
      "dt": "2026/03/06",
      "dead_t1": 0,
      "dead_t2": 0,
      "dead_t3": 0,
      "dead_t4": 0,
      "dead_t5": 0
    },
    {
      "id": "113962951",
      "name": "자이언트",
      "max_power": 25645663,
      "power": 25645439,
      "collect": 0,
      "dead": 0,
      "kill": 0,
      "t1": 0,
      "t2": 0,
      "t3": 0,
      "t4": 0,
      "t5": 0,
      "help": 3,
      "dt": "2026/03/06",
      "dead_t1": 0,
      "dead_t2": 0,
      "dead_t3": 0,
      "dead_t4": 0,
      "dead_t5": 0
    },
    {
      "id": "69303510",
      "name": "울트라캡숑 2호",
      "max_power": 25286347,
      "power": 25081673,
      "collect": 2691211638,
      "dead": 208458,
      "kill": 159940,
      "t1": 0,
      "t2": 0,
      "t3": 0,
      "t4": 0,
      "t5": 7997,
      "help": 868,
      "dt": "2026/03/06",
      "dead_t1": 0,
      "dead_t2": 0,
      "dead_t3": 0,
      "dead_t4": 215388,
      "dead_t5": 0
    },
    {
      "id": "35424907",
      "name": "Bearsiki farm1",
      "max_power": 36271622,
      "power": 24836266,
      "collect": 4553320708,
      "dead": 0,
      "kill": 0,
      "t1": 0,
      "t2": 0,
      "t3": 0,
      "t4": 0,
      "t5": 0,
      "help": 109,
      "dt": "2026/03/06",
      "dead_t1": 0,
      "dead_t2": 0,
      "dead_t3": 0,
      "dead_t4": 0,
      "dead_t5": 0
    },
    {
      "id": "85171726",
      "name": "정신차려이각박한코코",
      "max_power": 24606362,
      "power": 24597326,
      "collect": 472631679,
      "dead": 230787,
      "kill": 6045324,
      "t1": 9108,
      "t2": 306,
      "t3": 0,
      "t4": 97921,
      "t5": 253184,
      "help": 123,
      "dt": "2026/03/06",
      "dead_t1": 0,
      "dead_t2": 0,
      "dead_t3": 0,
      "dead_t4": 230787,
      "dead_t5": 0
    },
    {
      "id": "87122107",
      "name": "클레오파트라 ᴷˡᴺ",
      "max_power": 23964381,
      "power": 23832350,
      "collect": 250331092,
      "dead": 0,
      "kill": 303700,
      "t1": 0,
      "t2": 0,
      "t3": 0,
      "t4": 0,
      "t5": 15185,
      "help": 63,
      "dt": "2026/03/06",
      "dead_t1": 0,
      "dead_t2": 0,
      "dead_t3": 0,
      "dead_t4": 0,
      "dead_t5": 0
    },
    {
      "id": "76274821",
      "name": "옆산고라니",
      "max_power": 26414931,
      "power": 23832187,
      "collect": 479169910,
      "dead": 1676495,
      "kill": 14963111,
      "t1": 15,
      "t2": 237,
      "t3": 171,
      "t4": 489981,
      "t5": 503107,
      "help": 175,
      "dt": "2026/03/06",
      "dead_t1": 0,
      "dead_t2": 0,
      "dead_t3": 0,
      "dead_t4": 0,
      "dead_t5": 0
    },
    {
      "id": "146493440",
      "name": "무궁화 5호",
      "max_power": 23789505,
      "power": 23788361,
      "collect": 527198787,
      "dead": 0,
      "kill": 56980,
      "t1": 0,
      "t2": 0,
      "t3": 0,
      "t4": 0,
      "t5": 2849,
      "help": 143,
      "dt": "2026/03/06",
      "dead_t1": 0,
      "dead_t2": 0,
      "dead_t3": 0,
      "dead_t4": 0,
      "dead_t5": 0
    },
    {
      "id": "37360959",
      "name": "쿠스탄차 ᴷˡᴺ",
      "max_power": 24374537,
      "power": 23712122,
      "collect": 40461955,
      "dead": 0,
      "kill": 0,
      "t1": 0,
      "t2": 0,
      "t3": 0,
      "t4": 0,
      "t5": 0,
      "help": 9,
      "dt": "2026/03/06",
      "dead_t1": 0,
      "dead_t2": 0,
      "dead_t3": 0,
      "dead_t4": 0,
      "dead_t5": 0
    },
    {
      "id": "146494373",
      "name": "무궁화 4호",
      "max_power": 23269524,
      "power": 23267356,
      "collect": 536256427,
      "dead": 0,
      "kill": 114650,
      "t1": 0,
      "t2": 0,
      "t3": 0,
      "t4": 411,
      "t5": 5527,
      "help": 171,
      "dt": "2026/03/06",
      "dead_t1": 0,
      "dead_t2": 0,
      "dead_t3": 0,
      "dead_t4": 0,
      "dead_t5": 0
    },
    {
      "id": "87389039",
      "name": "bk공사",
      "max_power": 23809716,
      "power": 22891184,
      "collect": 582579439,
      "dead": 1185337,
      "kill": 20302257,
      "t1": 94,
      "t2": 179,
      "t3": 0,
      "t4": 397384,
      "t5": 816402,
      "help": 172,
      "dt": "2026/03/06",
      "dead_t1": 0,
      "dead_t2": 0,
      "dead_t3": 0,
      "dead_t4": 1185337,
      "dead_t5": 0
    },
    {
      "id": "181980044",
      "name": "마리다71",
      "max_power": 22916360,
      "power": 22887160,
      "collect": 4194519630,
      "dead": 0,
      "kill": 0,
      "t1": 0,
      "t2": 0,
      "t3": 0,
      "t4": 0,
      "t5": 0,
      "help": 701,
      "dt": "2026/03/06",
      "dead_t1": 0,
      "dead_t2": 0,
      "dead_t3": 0,
      "dead_t4": 0,
      "dead_t5": 0
    },
    {
      "id": "56009947",
      "name": "문 앙 sub4",
      "max_power": 23691988,
      "power": 22676504,
      "collect": 884277131,
      "dead": 0,
      "kill": 0,
      "t1": 0,
      "t2": 0,
      "t3": 0,
      "t4": 0,
      "t5": 0,
      "help": 96,
      "dt": "2026/03/06",
      "dead_t1": 0,
      "dead_t2": 0,
      "dead_t3": 0,
      "dead_t4": 0,
      "dead_t5": 0
    },
    {
      "id": "38747771",
      "name": "문 앙 sub3",
      "max_power": 28555049,
      "power": 22306965,
      "collect": 790534634,
      "dead": 0,
      "kill": 34540,
      "t1": 0,
      "t2": 0,
      "t3": 0,
      "t4": 0,
      "t5": 1727,
      "help": 163,
      "dt": "2026/03/06",
      "dead_t1": 0,
      "dead_t2": 0,
      "dead_t3": 0,
      "dead_t4": 0,
      "dead_t5": 0
    },
    {
      "id": "34342505",
      "name": "ᴹᶻMoonz 002",
      "max_power": 22194058,
      "power": 22167226,
      "collect": 163803544,
      "dead": 10145,
      "kill": 330720,
      "t1": 199,
      "t2": 0,
      "t3": 0,
      "t4": 33068,
      "t5": 0,
      "help": 157,
      "dt": "2026/03/06",
      "dead_t1": 0,
      "dead_t2": 0,
      "dead_t3": 0,
      "dead_t4": 10145,
      "dead_t5": 0
    },
    {
      "id": "73258177",
      "name": "Douglas MacArth",
      "max_power": 21909473,
      "power": 21909473,
      "collect": 126253065,
      "dead": 0,
      "kill": 0,
      "t1": 0,
      "t2": 0,
      "t3": 0,
      "t4": 0,
      "t5": 0,
      "help": 28,
      "dt": "2026/03/06",
      "dead_t1": 0,
      "dead_t2": 0,
      "dead_t3": 0,
      "dead_t4": 0,
      "dead_t5": 0
    },
    {
      "id": "98353689",
      "name": "AstroFarm28",
      "max_power": 21636469,
      "power": 21631233,
      "collect": 1351921538,
      "dead": 84753,
      "kill": 1843290,
      "t1": 2,
      "t2": 0,
      "t3": 0,
      "t4": 74323,
      "t5": 55003,
      "help": 254,
      "dt": "2026/03/06",
      "dead_t1": 0,
      "dead_t2": 0,
      "dead_t3": 0,
      "dead_t4": 84753,
      "dead_t5": 0
    },
    {
      "id": "93765073",
      "name": "ᴹᶻMoonz 001",
      "max_power": 21584072,
      "power": 21554072,
      "collect": 193571355,
      "dead": 12282,
      "kill": 488634,
      "t1": 273,
      "t2": 0,
      "t3": 0,
      "t4": 39574,
      "t5": 4642,
      "help": 170,
      "dt": "2026/03/06",
      "dead_t1": 0,
      "dead_t2": 0,
      "dead_t3": 0,
      "dead_t4": 12282,
      "dead_t5": 0
    },
    {
      "id": "90866856",
      "name": "코코팜 망고",
      "max_power": 23084476,
      "power": 20966337,
      "collect": 411688286,
      "dead": 0,
      "kill": 0,
      "t1": 0,
      "t2": 0,
      "t3": 0,
      "t4": 0,
      "t5": 0,
      "help": 54,
      "dt": "2026/03/06",
      "dead_t1": 0,
      "dead_t2": 0,
      "dead_t3": 0,
      "dead_t4": 0,
      "dead_t5": 0
    },
    {
      "id": "70598234",
      "name": "마틸다 ᴷˡᴺ",
      "max_power": 21239427,
      "power": 20880775,
      "collect": 126217432,
      "dead": 0,
      "kill": 0,
      "t1": 0,
      "t2": 0,
      "t3": 0,
      "t4": 0,
      "t5": 0,
      "help": 34,
      "dt": "2026/03/06",
      "dead_t1": 0,
      "dead_t2": 0,
      "dead_t3": 0,
      "dead_t4": 0,
      "dead_t5": 0
    },
    {
      "id": "185660628",
      "name": "아기물개 1호점",
      "max_power": 20801650,
      "power": 20801650,
      "collect": 5478982300,
      "dead": 0,
      "kill": 0,
      "t1": 0,
      "t2": 0,
      "t3": 0,
      "t4": 0,
      "t5": 0,
      "help": 463,
      "dt": "2026/03/06",
      "dead_t1": 0,
      "dead_t2": 0,
      "dead_t3": 0,
      "dead_t4": 0,
      "dead_t5": 0
    },
    {
      "id": "181979812",
      "name": "마리다76",
      "max_power": 20826071,
      "power": 20800071,
      "collect": 3975150595,
      "dead": 0,
      "kill": 0,
      "t1": 0,
      "t2": 0,
      "t3": 0,
      "t4": 0,
      "t5": 0,
      "help": 999,
      "dt": "2026/03/06",
      "dead_t1": 0,
      "dead_t2": 0,
      "dead_t3": 0,
      "dead_t4": 0,
      "dead_t5": 0
    },
    {
      "id": "181978980",
      "name": "마리다73",
      "max_power": 20815221,
      "power": 20789221,
      "collect": 4037474196,
      "dead": 0,
      "kill": 0,
      "t1": 0,
      "t2": 0,
      "t3": 0,
      "t4": 0,
      "t5": 0,
      "help": 1079,
      "dt": "2026/03/06",
      "dead_t1": 0,
      "dead_t2": 0,
      "dead_t3": 0,
      "dead_t4": 0,
      "dead_t5": 0
    },
    {
      "id": "185661327",
      "name": "아기물개 2호점",
      "max_power": 20744148,
      "power": 20744148,
      "collect": 5494224769,
      "dead": 0,
      "kill": 0,
      "t1": 0,
      "t2": 0,
      "t3": 0,
      "t4": 0,
      "t5": 0,
      "help": 465,
      "dt": "2026/03/06",
      "dead_t1": 0,
      "dead_t2": 0,
      "dead_t3": 0,
      "dead_t4": 0,
      "dead_t5": 0
    },
    {
      "id": "182396634",
      "name": "쭌 창고",
      "max_power": 20674532,
      "power": 20674532,
      "collect": 2348638730,
      "dead": 0,
      "kill": 0,
      "t1": 0,
      "t2": 0,
      "t3": 0,
      "t4": 0,
      "t5": 0,
      "help": 152,
      "dt": "2026/03/06",
      "dead_t1": 0,
      "dead_t2": 0,
      "dead_t3": 0,
      "dead_t4": 0,
      "dead_t5": 0
    },
    {
      "id": "181980289",
      "name": "마리다72",
      "max_power": 20691537,
      "power": 20665537,
      "collect": 4152811803,
      "dead": 0,
      "kill": 0,
      "t1": 0,
      "t2": 0,
      "t3": 0,
      "t4": 0,
      "t5": 0,
      "help": 680,
      "dt": "2026/03/06",
      "dead_t1": 0,
      "dead_t2": 0,
      "dead_t3": 0,
      "dead_t4": 0,
      "dead_t5": 0
    },
    {
      "id": "45336154",
      "name": "LV41 PONGSHEW",
      "max_power": 20534550,
      "power": 20534550,
      "collect": 74174469,
      "dead": 0,
      "kill": 0,
      "t1": 0,
      "t2": 0,
      "t3": 0,
      "t4": 0,
      "t5": 0,
      "help": 8,
      "dt": "2026/03/06",
      "dead_t1": 0,
      "dead_t2": 0,
      "dead_t3": 0,
      "dead_t4": 0,
      "dead_t5": 0
    },
    {
      "id": "182396908",
      "name": "쭌 곳간",
      "max_power": 20478659,
      "power": 20478659,
      "collect": 2243504894,
      "dead": 571567,
      "kill": 9079768,
      "t1": 13741,
      "t2": 444,
      "t3": 183,
      "t4": 194356,
      "t5": 356592,
      "help": 263,
      "dt": "2026/03/06",
      "dead_t1": 0,
      "dead_t2": 0,
      "dead_t3": 0,
      "dead_t4": 571567,
      "dead_t5": 0
    },
    {
      "id": "111335824",
      "name": "yayaやや2",
      "max_power": 20854465,
      "power": 20416995,
      "collect": 1340009469,
      "dead": 0,
      "kill": 0,
      "t1": 0,
      "t2": 0,
      "t3": 0,
      "t4": 0,
      "t5": 0,
      "help": 47,
      "dt": "2026/03/06",
      "dead_t1": 0,
      "dead_t2": 0,
      "dead_t3": 0,
      "dead_t4": 0,
      "dead_t5": 0
    },
    {
      "id": "39253074",
      "name": "문 앙 sub5",
      "max_power": 20403337,
      "power": 20403337,
      "collect": 819041632,
      "dead": 0,
      "kill": 0,
      "t1": 0,
      "t2": 0,
      "t3": 0,
      "t4": 0,
      "t5": 0,
      "help": 95,
      "dt": "2026/03/06",
      "dead_t1": 0,
      "dead_t2": 0,
      "dead_t3": 0,
      "dead_t4": 0,
      "dead_t5": 0
    },
    {
      "id": "73191564",
      "name": "Adeel jaat",
      "max_power": 20361020,
      "power": 20361020,
      "collect": 436538766,
      "dead": 71500,
      "kill": 3076070,
      "t1": 446290,
      "t2": 242928,
      "t3": 609239,
      "t4": 6400,
      "t5": 0,
      "help": 29,
      "dt": "2026/03/06",
      "dead_t1": 2357,
      "dead_t2": 0,
      "dead_t3": 1662,
      "dead_t4": 67481,
      "dead_t5": 0
    },
    {
      "id": "52753343",
      "name": "타마르 ᴷˡᴺ",
      "max_power": 23696369,
      "power": 20338900,
      "collect": 156481954,
      "dead": 0,
      "kill": 0,
      "t1": 0,
      "t2": 0,
      "t3": 0,
      "t4": 0,
      "t5": 0,
      "help": 21,
      "dt": "2026/03/06",
      "dead_t1": 0,
      "dead_t2": 0,
      "dead_t3": 0,
      "dead_t4": 0,
      "dead_t5": 0
    },
    {
      "id": "181979297",
      "name": "마리다74",
      "max_power": 20304430,
      "power": 20278430,
      "collect": 4077745985,
      "dead": 0,
      "kill": 0,
      "t1": 0,
      "t2": 0,
      "t3": 0,
      "t4": 0,
      "t5": 0,
      "help": 658,
      "dt": "2026/03/06",
      "dead_t1": 0,
      "dead_t2": 0,
      "dead_t3": 0,
      "dead_t4": 0,
      "dead_t5": 0
    },
    {
      "id": "181979587",
      "name": "마리다75",
      "max_power": 20243669,
      "power": 20216869,
      "collect": 4042049348,
      "dead": 0,
      "kill": 0,
      "t1": 0,
      "t2": 0,
      "t3": 0,
      "t4": 0,
      "t5": 0,
      "help": 631,
      "dt": "2026/03/06",
      "dead_t1": 0,
      "dead_t2": 0,
      "dead_t3": 0,
      "dead_t4": 0,
      "dead_t5": 0
    },
    {
      "id": "36995799",
      "name": "문 앙 sub6",
      "max_power": 19917974,
      "power": 19917974,
      "collect": 896729618,
      "dead": 0,
      "kill": 0,
      "t1": 0,
      "t2": 0,
      "t3": 0,
      "t4": 0,
      "t5": 0,
      "help": 107,
      "dt": "2026/03/06",
      "dead_t1": 0,
      "dead_t2": 0,
      "dead_t3": 0,
      "dead_t4": 0,
      "dead_t5": 0
    },
    {
      "id": "126413244",
      "name": "yayaやや4",
      "max_power": 19867710,
      "power": 19867710,
      "collect": 1211256019,
      "dead": 0,
      "kill": 0,
      "t1": 0,
      "t2": 0,
      "t3": 0,
      "t4": 0,
      "t5": 0,
      "help": 48,
      "dt": "2026/03/06",
      "dead_t1": 0,
      "dead_t2": 0,
      "dead_t3": 0,
      "dead_t4": 0,
      "dead_t5": 0
    },
    {
      "id": "187294137",
      "name": "쭌 광",
      "max_power": 19796723,
      "power": 19796723,
      "collect": 2280553756,
      "dead": 0,
      "kill": 0,
      "t1": 0,
      "t2": 0,
      "t3": 0,
      "t4": 0,
      "t5": 0,
      "help": 253,
      "dt": "2026/03/06",
      "dead_t1": 0,
      "dead_t2": 0,
      "dead_t3": 0,
      "dead_t4": 0,
      "dead_t5": 0
    },
    {
      "id": "68211312",
      "name": "LV10 PONGSHEW",
      "max_power": 19379800,
      "power": 19379800,
      "collect": 399106250,
      "dead": 0,
      "kill": 0,
      "t1": 0,
      "t2": 0,
      "t3": 0,
      "t4": 0,
      "t5": 0,
      "help": 45,
      "dt": "2026/03/06",
      "dead_t1": 0,
      "dead_t2": 0,
      "dead_t3": 0,
      "dead_t4": 0,
      "dead_t5": 0
    },
    {
      "id": "81240911",
      "name": "칵테일한잔",
      "max_power": 19242550,
      "power": 19242550,
      "collect": 235707926,
      "dead": 0,
      "kill": 0,
      "t1": 0,
      "t2": 0,
      "t3": 0,
      "t4": 0,
      "t5": 0,
      "help": 75,
      "dt": "2026/03/06",
      "dead_t1": 0,
      "dead_t2": 0,
      "dead_t3": 0,
      "dead_t4": 0,
      "dead_t5": 0
    },
    {
      "id": "85174060",
      "name": "싱 게",
      "max_power": 22190685,
      "power": 18928612,
      "collect": 0,
      "dead": 0,
      "kill": 0,
      "t1": 0,
      "t2": 0,
      "t3": 0,
      "t4": 0,
      "t5": 0,
      "help": 0,
      "dt": "2026/03/06",
      "dead_t1": 0,
      "dead_t2": 0,
      "dead_t3": 0,
      "dead_t4": 0,
      "dead_t5": 0
    },
    {
      "id": "81228613",
      "name": "데킬라한잔",
      "max_power": 18903474,
      "power": 18903474,
      "collect": 225172098,
      "dead": 0,
      "kill": 0,
      "t1": 0,
      "t2": 0,
      "t3": 0,
      "t4": 0,
      "t5": 0,
      "help": 78,
      "dt": "2026/03/06",
      "dead_t1": 0,
      "dead_t2": 0,
      "dead_t3": 0,
      "dead_t4": 0,
      "dead_t5": 0
    },
    {
      "id": "122842370",
      "name": "새로한잔",
      "max_power": 18392359,
      "power": 18392359,
      "collect": 281301490,
      "dead": 0,
      "kill": 0,
      "t1": 0,
      "t2": 0,
      "t3": 0,
      "t4": 0,
      "t5": 0,
      "help": 83,
      "dt": "2026/03/06",
      "dead_t1": 0,
      "dead_t2": 0,
      "dead_t3": 0,
      "dead_t4": 0,
      "dead_t5": 0
    },
    {
      "id": "87062844",
      "name": "초선 ᴷˡᴺ",
      "max_power": 18012533,
      "power": 18012533,
      "collect": 54807480,
      "dead": 0,
      "kill": 0,
      "t1": 0,
      "t2": 0,
      "t3": 0,
      "t4": 0,
      "t5": 0,
      "help": 7,
      "dt": "2026/03/06",
      "dead_t1": 0,
      "dead_t2": 0,
      "dead_t3": 0,
      "dead_t4": 0,
      "dead_t5": 0
    },
    {
      "id": "122841394",
      "name": "레드와인한잔",
      "max_power": 18098325,
      "power": 17857143,
      "collect": 237216215,
      "dead": 0,
      "kill": 0,
      "t1": 0,
      "t2": 0,
      "t3": 0,
      "t4": 0,
      "t5": 0,
      "help": 77,
      "dt": "2026/03/06",
      "dead_t1": 0,
      "dead_t2": 0,
      "dead_t3": 0,
      "dead_t4": 0,
      "dead_t5": 0
    },
    {
      "id": "143739197",
      "name": "yayaやや6",
      "max_power": 17418984,
      "power": 17418984,
      "collect": 1173191398,
      "dead": 0,
      "kill": 0,
      "t1": 0,
      "t2": 0,
      "t3": 0,
      "t4": 0,
      "t5": 0,
      "help": 50,
      "dt": "2026/03/06",
      "dead_t1": 0,
      "dead_t2": 0,
      "dead_t3": 0,
      "dead_t4": 0,
      "dead_t5": 0
    },
    {
      "id": "143738937",
      "name": "yayaやや8",
      "max_power": 17371377,
      "power": 17371377,
      "collect": 1221690026,
      "dead": 0,
      "kill": 0,
      "t1": 0,
      "t2": 0,
      "t3": 0,
      "t4": 0,
      "t5": 0,
      "help": 49,
      "dt": "2026/03/06",
      "dead_t1": 0,
      "dead_t2": 0,
      "dead_t3": 0,
      "dead_t4": 0,
      "dead_t5": 0
    },
    {
      "id": "131042630",
      "name": "yayaやや5",
      "max_power": 16782917,
      "power": 16782917,
      "collect": 1419043911,
      "dead": 0,
      "kill": 0,
      "t1": 0,
      "t2": 0,
      "t3": 0,
      "t4": 0,
      "t5": 0,
      "help": 53,
      "dt": "2026/03/06",
      "dead_t1": 0,
      "dead_t2": 0,
      "dead_t3": 0,
      "dead_t4": 0,
      "dead_t5": 0
    },
    {
      "id": "144029460",
      "name": "yayaやや7",
      "max_power": 16668448,
      "power": 16668448,
      "collect": 1191801496,
      "dead": 0,
      "kill": 0,
      "t1": 0,
      "t2": 0,
      "t3": 0,
      "t4": 0,
      "t5": 0,
      "help": 49,
      "dt": "2026/03/06",
      "dead_t1": 0,
      "dead_t2": 0,
      "dead_t3": 0,
      "dead_t4": 0,
      "dead_t5": 0
    },
    {
      "id": "131043066",
      "name": "yayaやや3",
      "max_power": 16654604,
      "power": 16654604,
      "collect": 1345829716,
      "dead": 0,
      "kill": 0,
      "t1": 0,
      "t2": 0,
      "t3": 0,
      "t4": 0,
      "t5": 0,
      "help": 48,
      "dt": "2026/03/06",
      "dead_t1": 0,
      "dead_t2": 0,
      "dead_t3": 0,
      "dead_t4": 0,
      "dead_t5": 0
    },
    {
      "id": "74381727",
      "name": "페펲펲2",
      "max_power": 16062061,
      "power": 16062061,
      "collect": 2938806456,
      "dead": 0,
      "kill": 0,
      "t1": 0,
      "t2": 0,
      "t3": 0,
      "t4": 0,
      "t5": 0,
      "help": 262,
      "dt": "2026/03/06",
      "dead_t1": 0,
      "dead_t2": 0,
      "dead_t3": 0,
      "dead_t4": 0,
      "dead_t5": 0
    },
    {
      "id": "77728228",
      "name": "ᴱᵛ 채식주의폴라곰",
      "max_power": 17382951,
      "power": 15977985,
      "collect": 111464085,
      "dead": 0,
      "kill": 0,
      "t1": 0,
      "t2": 0,
      "t3": 0,
      "t4": 0,
      "t5": 0,
      "help": 14,
      "dt": "2026/03/06",
      "dead_t1": 0,
      "dead_t2": 0,
      "dead_t3": 0,
      "dead_t4": 0,
      "dead_t5": 0
    },
    {
      "id": "196992659",
      "name": "2029 하니차니4",
      "max_power": 15928762,
      "power": 15928762,
      "collect": 3496811525,
      "dead": 0,
      "kill": 0,
      "t1": 0,
      "t2": 0,
      "t3": 0,
      "t4": 0,
      "t5": 0,
      "help": 293,
      "dt": "2026/03/06",
      "dead_t1": 0,
      "dead_t2": 0,
      "dead_t3": 0,
      "dead_t4": 0,
      "dead_t5": 0
    },
    {
      "id": "173102854",
      "name": "백마탄 꼬",
      "max_power": 15606034,
      "power": 15606034,
      "collect": 391719274,
      "dead": 609620,
      "kill": 727900,
      "t1": 0,
      "t2": 0,
      "t3": 0,
      "t4": 0,
      "t5": 36395,
      "help": 38,
      "dt": "2026/03/06",
      "dead_t1": 85,
      "dead_t2": 183,
      "dead_t3": 484,
      "dead_t4": 88711,
      "dead_t5": 0
    },
    {
      "id": "71703443",
      "name": "코코팜 포도",
      "max_power": 15593396,
      "power": 15593396,
      "collect": 625543325,
      "dead": 0,
      "kill": 0,
      "t1": 0,
      "t2": 0,
      "t3": 0,
      "t4": 0,
      "t5": 0,
      "help": 86,
      "dt": "2026/03/06",
      "dead_t1": 0,
      "dead_t2": 0,
      "dead_t3": 0,
      "dead_t4": 0,
      "dead_t5": 0
    },
    {
      "id": "152974494",
      "name": "onNET7",
      "max_power": 14803969,
      "power": 14803969,
      "collect": 2248107716,
      "dead": 0,
      "kill": 0,
      "t1": 0,
      "t2": 0,
      "t3": 0,
      "t4": 0,
      "t5": 0,
      "help": 318,
      "dt": "2026/03/06",
      "dead_t1": 0,
      "dead_t2": 0,
      "dead_t3": 0,
      "dead_t4": 0,
      "dead_t5": 0
    },
    {
      "id": "85766982",
      "name": "ᴱᵛ 커피는맥심폴라곰",
      "max_power": 14675828,
      "power": 14675828,
      "collect": 60424380,
      "dead": 0,
      "kill": 0,
      "t1": 0,
      "t2": 0,
      "t3": 0,
      "t4": 0,
      "t5": 0,
      "help": 9,
      "dt": "2026/03/06",
      "dead_t1": 0,
      "dead_t2": 0,
      "dead_t3": 0,
      "dead_t4": 0,
      "dead_t5": 0
    },
    {
      "id": "73251960",
      "name": "liiciil",
      "max_power": 14424752,
      "power": 14364160,
      "collect": 180709608,
      "dead": 505942,
      "kill": 376690,
      "t1": 0,
      "t2": 0,
      "t3": 0,
      "t4": 3499,
      "t5": 17085,
      "help": 20,
      "dt": "2026/03/06",
      "dead_t1": 0,
      "dead_t2": 0,
      "dead_t3": 0,
      "dead_t4": 0,
      "dead_t5": 0
    },
    {
      "id": "77375343",
      "name": "코코코코코코볼",
      "max_power": 14256933,
      "power": 14256933,
      "collect": 481869254,
      "dead": 0,
      "kill": 0,
      "t1": 0,
      "t2": 0,
      "t3": 0,
      "t4": 0,
      "t5": 0,
      "help": 40,
      "dt": "2026/03/06",
      "dead_t1": 0,
      "dead_t2": 0,
      "dead_t3": 0,
      "dead_t4": 0,
      "dead_t5": 0
    },
    {
      "id": "81227099",
      "name": "울트라캡숑 3호",
      "max_power": 14144957,
      "power": 14144957,
      "collect": 2098370284,
      "dead": 0,
      "kill": 50840,
      "t1": 0,
      "t2": 0,
      "t3": 0,
      "t4": 0,
      "t5": 2542,
      "help": 266,
      "dt": "2026/03/06",
      "dead_t1": 0,
      "dead_t2": 0,
      "dead_t3": 0,
      "dead_t4": 0,
      "dead_t5": 0
    },
    {
      "id": "185336666",
      "name": "문 앙 sub7",
      "max_power": 13070990,
      "power": 13070990,
      "collect": 687533189,
      "dead": 0,
      "kill": 0,
      "t1": 0,
      "t2": 0,
      "t3": 0,
      "t4": 0,
      "t5": 0,
      "help": 77,
      "dt": "2026/03/06",
      "dead_t1": 0,
      "dead_t2": 0,
      "dead_t3": 0,
      "dead_t4": 0,
      "dead_t5": 0
    },
    {
      "id": "108200477",
      "name": "울트라캡숑 4호",
      "max_power": 12809241,
      "power": 12809241,
      "collect": 1543196610,
      "dead": 0,
      "kill": 41700,
      "t1": 0,
      "t2": 0,
      "t3": 0,
      "t4": 0,
      "t5": 2085,
      "help": 83,
      "dt": "2026/03/06",
      "dead_t1": 0,
      "dead_t2": 0,
      "dead_t3": 0,
      "dead_t4": 0,
      "dead_t5": 0
    },
    {
      "id": "102578717",
      "name": "AstroFarm28Too",
      "max_power": 12627303,
      "power": 12627303,
      "collect": 1182085896,
      "dead": 0,
      "kill": 0,
      "t1": 0,
      "t2": 0,
      "t3": 0,
      "t4": 0,
      "t5": 0,
      "help": 99,
      "dt": "2026/03/06",
      "dead_t1": 0,
      "dead_t2": 0,
      "dead_t3": 0,
      "dead_t4": 0,
      "dead_t5": 0
    },
    {
      "id": "201841610",
      "name": "2029 하니차니5",
      "max_power": 11461518,
      "power": 11461518,
      "collect": 3271061686,
      "dead": 0,
      "kill": 0,
      "t1": 0,
      "t2": 0,
      "t3": 0,
      "t4": 0,
      "t5": 0,
      "help": 317,
      "dt": "2026/03/06",
      "dead_t1": 0,
      "dead_t2": 0,
      "dead_t3": 0,
      "dead_t4": 0,
      "dead_t5": 0
    },
    {
      "id": "108201148",
      "name": "울트라캡숑 5호",
      "max_power": 10966181,
      "power": 10966181,
      "collect": 1267120259,
      "dead": 0,
      "kill": 0,
      "t1": 0,
      "t2": 0,
      "t3": 0,
      "t4": 0,
      "t5": 0,
      "help": 102,
      "dt": "2026/03/06",
      "dead_t1": 0,
      "dead_t2": 0,
      "dead_t3": 0,
      "dead_t4": 0,
      "dead_t5": 0
    },
    {
      "id": "121075140",
      "name": "울트라캡숑 6호",
      "max_power": 10912154,
      "power": 10912154,
      "collect": 1336264952,
      "dead": 0,
      "kill": 10660,
      "t1": 0,
      "t2": 0,
      "t3": 0,
      "t4": 0,
      "t5": 533,
      "help": 84,
      "dt": "2026/03/06",
      "dead_t1": 0,
      "dead_t2": 0,
      "dead_t3": 0,
      "dead_t4": 0,
      "dead_t5": 0
    },
    {
      "id": "159346004",
      "name": "헤라 ᴷˡᴺ",
      "max_power": 10555927,
      "power": 10555927,
      "collect": 49086049,
      "dead": 0,
      "kill": 0,
      "t1": 0,
      "t2": 0,
      "t3": 0,
      "t4": 0,
      "t5": 0,
      "help": 7,
      "dt": "2026/03/06",
      "dead_t1": 0,
      "dead_t2": 0,
      "dead_t3": 0,
      "dead_t4": 0,
      "dead_t5": 0
    },
    {
      "id": "145870062",
      "name": "Zombie RA A",
      "max_power": 10122727,
      "power": 10122727,
      "collect": 987242813,
      "dead": 0,
      "kill": 0,
      "t1": 0,
      "t2": 0,
      "t3": 0,
      "t4": 0,
      "t5": 0,
      "help": 36,
      "dt": "2026/03/06",
      "dead_t1": 0,
      "dead_t2": 0,
      "dead_t3": 0,
      "dead_t4": 0,
      "dead_t5": 0
    },
    {
      "id": "89957726",
      "name": "Thống đốc89957726",
      "max_power": 9845087,
      "power": 9845087,
      "collect": 1866828002,
      "dead": 482799,
      "kill": 73020,
      "t1": 0,
      "t2": 0,
      "t3": 0,
      "t4": 0,
      "t5": 3651,
      "help": 41,
      "dt": "2026/03/06",
      "dead_t1": 0,
      "dead_t2": 0,
      "dead_t3": 0,
      "dead_t4": 0,
      "dead_t5": 0
    },
    {
      "id": "36964589",
      "name": "코코몽",
      "max_power": 9440876,
      "power": 9440876,
      "collect": 329976157,
      "dead": 0,
      "kill": 0,
      "t1": 0,
      "t2": 0,
      "t3": 0,
      "t4": 0,
      "t5": 0,
      "help": 38,
      "dt": "2026/03/06",
      "dead_t1": 0,
      "dead_t2": 0,
      "dead_t3": 0,
      "dead_t4": 0,
      "dead_t5": 0
    },
    {
      "id": "130363961",
      "name": "AstroFarm28Tree",
      "max_power": 8390832,
      "power": 8390832,
      "collect": 1174514295,
      "dead": 0,
      "kill": 0,
      "t1": 0,
      "t2": 0,
      "t3": 0,
      "t4": 0,
      "t5": 0,
      "help": 100,
      "dt": "2026/03/06",
      "dead_t1": 0,
      "dead_t2": 0,
      "dead_t3": 0,
      "dead_t4": 0,
      "dead_t5": 0
    },
    {
      "id": "130401587",
      "name": "AstroFarm28Foor",
      "max_power": 7445791,
      "power": 7445791,
      "collect": 1123269161,
      "dead": 0,
      "kill": 0,
      "t1": 0,
      "t2": 0,
      "t3": 0,
      "t4": 0,
      "t5": 0,
      "help": 112,
      "dt": "2026/03/06",
      "dead_t1": 0,
      "dead_t2": 0,
      "dead_t3": 0,
      "dead_t4": 0,
      "dead_t5": 0
    },
    {
      "id": "174866715",
      "name": "AstroFarm28Faiv",
      "max_power": 7034063,
      "power": 7034063,
      "collect": 1052946018,
      "dead": 0,
      "kill": 0,
      "t1": 0,
      "t2": 0,
      "t3": 0,
      "t4": 0,
      "t5": 0,
      "help": 133,
      "dt": "2026/03/06",
      "dead_t1": 0,
      "dead_t2": 0,
      "dead_t3": 0,
      "dead_t4": 0,
      "dead_t5": 0
    },
    {
      "id": "161119440",
      "name": "위스키한잔",
      "max_power": 6388473,
      "power": 6388473,
      "collect": 270499882,
      "dead": 0,
      "kill": 0,
      "t1": 0,
      "t2": 0,
      "t3": 0,
      "t4": 0,
      "t5": 0,
      "help": 70,
      "dt": "2026/03/06",
      "dead_t1": 0,
      "dead_t2": 0,
      "dead_t3": 0,
      "dead_t4": 0,
      "dead_t5": 0
    },
    {
      "id": "104947368",
      "name": "LuvÜ  유주",
      "max_power": 6352737,
      "power": 6352737,
      "collect": 37572674,
      "dead": 0,
      "kill": 0,
      "t1": 0,
      "t2": 0,
      "t3": 0,
      "t4": 0,
      "t5": 0,
      "help": 9,
      "dt": "2026/03/06",
      "dead_t1": 0,
      "dead_t2": 0,
      "dead_t3": 0,
      "dead_t4": 0,
      "dead_t5": 0
    },
    {
      "id": "174868125",
      "name": "AstroFarm28Six",
      "max_power": 6097684,
      "power": 6097684,
      "collect": 1019758543,
      "dead": 0,
      "kill": 0,
      "t1": 0,
      "t2": 0,
      "t3": 0,
      "t4": 0,
      "t5": 0,
      "help": 138,
      "dt": "2026/03/06",
      "dead_t1": 0,
      "dead_t2": 0,
      "dead_t3": 0,
      "dead_t4": 0,
      "dead_t5": 0
    },
    {
      "id": "139070677",
      "name": "울트라캡숑 7호",
      "max_power": 6069847,
      "power": 6069847,
      "collect": 711885678,
      "dead": 0,
      "kill": 0,
      "t1": 0,
      "t2": 0,
      "t3": 0,
      "t4": 0,
      "t5": 0,
      "help": 70,
      "dt": "2026/03/06",
      "dead_t1": 0,
      "dead_t2": 0,
      "dead_t3": 0,
      "dead_t4": 0,
      "dead_t5": 0
    },
    {
      "id": "161120073",
      "name": "청하한잔",
      "max_power": 5719015,
      "power": 5719015,
      "collect": 200327595,
      "dead": 0,
      "kill": 0,
      "t1": 0,
      "t2": 0,
      "t3": 0,
      "t4": 0,
      "t5": 0,
      "help": 85,
      "dt": "2026/03/06",
      "dead_t1": 0,
      "dead_t2": 0,
      "dead_t3": 0,
      "dead_t4": 0,
      "dead_t5": 0
    },
    {
      "id": "186208683",
      "name": "코코코코코볼",
      "max_power": 4487625,
      "power": 4487625,
      "collect": 69684720,
      "dead": 0,
      "kill": 0,
      "t1": 0,
      "t2": 0,
      "t3": 0,
      "t4": 0,
      "t5": 0,
      "help": 40,
      "dt": "2026/03/06",
      "dead_t1": 0,
      "dead_t2": 0,
      "dead_t3": 0,
      "dead_t4": 0,
      "dead_t5": 0
    },
    {
      "id": "169561230",
      "name": "할명수 코코",
      "max_power": 4344925,
      "power": 4344925,
      "collect": 56124237,
      "dead": 0,
      "kill": 0,
      "t1": 0,
      "t2": 0,
      "t3": 0,
      "t4": 0,
      "t5": 0,
      "help": 36,
      "dt": "2026/03/06",
      "dead_t1": 0,
      "dead_t2": 0,
      "dead_t3": 0,
      "dead_t4": 0,
      "dead_t5": 0
    },
    {
      "id": "181020419",
      "name": "마리다51",
      "max_power": 946631,
      "power": 946631,
      "collect": 0,
      "dead": 0,
      "kill": 0,
      "t1": 0,
      "t2": 0,
      "t3": 0,
      "t4": 0,
      "t5": 0,
      "help": 56,
      "dt": "2026/03/06",
      "dead_t1": 0,
      "dead_t2": 0,
      "dead_t3": 0,
      "dead_t4": 0,
      "dead_t5": 0
    },
    {
      "id": "181105400",
      "name": "마리다55",
      "max_power": 826304,
      "power": 826304,
      "collect": 0,
      "dead": 0,
      "kill": 0,
      "t1": 0,
      "t2": 0,
      "t3": 0,
      "t4": 0,
      "t5": 0,
      "help": 48,
      "dt": "2026/03/06",
      "dead_t1": 0,
      "dead_t2": 0,
      "dead_t3": 0,
      "dead_t4": 0,
      "dead_t5": 0
    },
    {
      "id": "181022337",
      "name": "마리다52",
      "max_power": 824050,
      "power": 824050,
      "collect": 0,
      "dead": 0,
      "kill": 0,
      "t1": 0,
      "t2": 0,
      "t3": 0,
      "t4": 0,
      "t5": 0,
      "help": 55,
      "dt": "2026/03/06",
      "dead_t1": 0,
      "dead_t2": 0,
      "dead_t3": 0,
      "dead_t4": 0,
      "dead_t5": 0
    },
    {
      "id": "181054669",
      "name": "마리다54",
      "max_power": 819794,
      "power": 819794,
      "collect": 0,
      "dead": 0,
      "kill": 0,
      "t1": 0,
      "t2": 0,
      "t3": 0,
      "t4": 0,
      "t5": 0,
      "help": 41,
      "dt": "2026/03/06",
      "dead_t1": 0,
      "dead_t2": 0,
      "dead_t3": 0,
      "dead_t4": 0,
      "dead_t5": 0
    },
    {
      "id": "181054021",
      "name": "마리다53",
      "max_power": 817720,
      "power": 817720,
      "collect": 0,
      "dead": 0,
      "kill": 0,
      "t1": 0,
      "t2": 0,
      "t3": 0,
      "t4": 0,
      "t5": 0,
      "help": 51,
      "dt": "2026/03/06",
      "dead_t1": 0,
      "dead_t2": 0,
      "dead_t3": 0,
      "dead_t4": 0,
      "dead_t5": 0
    },
    {
      "id": "181105646",
      "name": "마리다56",
      "max_power": 813047,
      "power": 813047,
      "collect": 0,
      "dead": 0,
      "kill": 0,
      "t1": 0,
      "t2": 0,
      "t3": 0,
      "t4": 0,
      "t5": 0,
      "help": 48,
      "dt": "2026/03/06",
      "dead_t1": 0,
      "dead_t2": 0,
      "dead_t3": 0,
      "dead_t4": 0,
      "dead_t5": 0
    },
    {
      "id": "209481990",
      "name": "Governor209481990",
      "max_power": 41786,
      "power": 41786,
      "collect": 0,
      "dead": 0,
      "kill": 0,
      "t1": 0,
      "t2": 0,
      "t3": 0,
      "t4": 0,
      "t5": 0,
      "help": 0,
      "dt": "2026/03/06",
      "dead_t1": 0,
      "dead_t2": 0,
      "dead_t3": 0,
      "dead_t4": 0,
      "dead_t5": 0
    }
  ]
}