{
  "kingdom": 2332,
  "from_date": "2025-09-08",
  "to_date": "2026-03-06",
  "data": [
    {
      "id": "32797139",
      "name": "무닌",
      "max_power": 124070326,
      "power": 117967272,
      "collect": 3162501586,
      "dead": 3140786,
      "kill": 5725123397,
      "t1": 13189213,
      "t2": 1492026,
      "t3": 626058,
      "t4": 93122763,
      "t5": 239288482,
      "help": 13691,
      "dt": "2026/03/06",
      "dead_t1": 0,
      "dead_t2": 0,
      "dead_t3": 0,
      "dead_t4": 0,
      "dead_t5": 1748402
    },
    {
      "id": "72912934",
      "name": "알콜레이스",
      "max_power": 117229908,
      "power": 117229908,
      "collect": 6083568529,
      "dead": 1007259,
      "kill": 1553530315,
      "t1": 148781,
      "t2": 25452,
      "t3": 366,
      "t4": 9129943,
      "t5": 73107438,
      "help": 11475,
      "dt": "2026/03/06",
      "dead_t1": 0,
      "dead_t2": 0,
      "dead_t3": 0,
      "dead_t4": 83232,
      "dead_t5": 702799
    },
    {
      "id": "64916001",
      "name": "IK 강 하 다",
      "max_power": 112381146,
      "power": 111933506,
      "collect": 2109555630,
      "dead": 1120842,
      "kill": 1273726137,
      "t1": 256442,
      "t2": 17026,
      "t3": 844,
      "t4": 9209190,
      "t5": 59077276,
      "help": 2034,
      "dt": "2026/03/06",
      "dead_t1": 0,
      "dead_t2": 0,
      "dead_t3": 0,
      "dead_t4": 0,
      "dead_t5": 585094
    },
    {
      "id": "63839652",
      "name": "sonny 7",
      "max_power": 113794090,
      "power": 110026370,
      "collect": 2398296795,
      "dead": 2906584,
      "kill": 4507400973,
      "t1": 4623044,
      "t2": 1018948,
      "t3": 231867,
      "t4": 41570474,
      "t5": 204390313,
      "help": 14503,
      "dt": "2026/03/06",
      "dead_t1": 0,
      "dead_t2": 0,
      "dead_t3": 0,
      "dead_t4": 0,
      "dead_t5": 1831549
    },
    {
      "id": "73298650",
      "name": "도박치료 1336",
      "max_power": 114966885,
      "power": 107663657,
      "collect": 4604133671,
      "dead": 2438588,
      "kill": 1289762542,
      "t1": 1166188,
      "t2": 72731,
      "t3": 247658,
      "t4": 10624845,
      "t5": 59107238,
      "help": 741,
      "dt": "2026/03/06",
      "dead_t1": 0,
      "dead_t2": 0,
      "dead_t3": 0,
      "dead_t4": 6186,
      "dead_t5": 831133
    },
    {
      "id": "75809480",
      "name": "ȻŦ 소탱이",
      "max_power": 111594471,
      "power": 106944461,
      "collect": 2892031797,
      "dead": 2365999,
      "kill": 633053705,
      "t1": 357647,
      "t2": 39433,
      "t3": 3550,
      "t4": 4064919,
      "t5": 29611996,
      "help": 4781,
      "dt": "2026/03/06",
      "dead_t1": 0,
      "dead_t2": 0,
      "dead_t3": 0,
      "dead_t4": 0,
      "dead_t5": 296386
    },
    {
      "id": "32207564",
      "name": "亗 ᴰ Bambi",
      "max_power": 118225355,
      "power": 106160245,
      "collect": 211378501,
      "dead": 1890797,
      "kill": 183008363,
      "t1": 58364,
      "t2": 3599,
      "t3": 113,
      "t4": 1694348,
      "t5": 8302278,
      "help": 659,
      "dt": "2026/03/06",
      "dead_t1": 0,
      "dead_t2": 0,
      "dead_t3": 0,
      "dead_t4": 0,
      "dead_t5": 1050426
    },
    {
      "id": "50713057",
      "name": "S 호나우도",
      "max_power": 108973160,
      "power": 105590776,
      "collect": 4287163254,
      "dead": 2577914,
      "kill": 862871452,
      "t1": 531392,
      "t2": 97429,
      "t3": 50414,
      "t4": 7272620,
      "t5": 39482123,
      "help": 2683,
      "dt": "2026/03/06",
      "dead_t1": 0,
      "dead_t2": 0,
      "dead_t3": 0,
      "dead_t4": 7794,
      "dead_t5": 319205
    },
    {
      "id": "32264862",
      "name": "FeelsoGood",
      "max_power": 126851505,
      "power": 101295546,
      "collect": 4802580105,
      "dead": 6522584,
      "kill": 3988772907,
      "t1": 2889976,
      "t2": 522376,
      "t3": 103325,
      "t4": 36911256,
      "t5": 180881215,
      "help": 13827,
      "dt": "2026/03/06",
      "dead_t1": 44380,
      "dead_t2": 373469,
      "dead_t3": 0,
      "dead_t4": 0,
      "dead_t5": 2394695
    },
    {
      "id": "67188240",
      "name": "이빠잉",
      "max_power": 136715864,
      "power": 101143178,
      "collect": 4387114978,
      "dead": 8710142,
      "kill": 1156061460,
      "t1": 1005173,
      "t2": 145957,
      "t3": 147048,
      "t4": 9847908,
      "t5": 52825062,
      "help": 5674,
      "dt": "2026/03/06",
      "dead_t1": 0,
      "dead_t2": 0,
      "dead_t3": 0,
      "dead_t4": 180740,
      "dead_t5": 2605864
    },
    {
      "id": "42199246",
      "name": "Quỷ  Đỏ",
      "max_power": 99582693,
      "power": 97887930,
      "collect": 824829945,
      "dead": 2294337,
      "kill": 1047915055,
      "t1": 13892384,
      "t2": 264765,
      "t3": 16532,
      "t4": 13931364,
      "t5": 45261364,
      "help": 13661,
      "dt": "2026/03/06",
      "dead_t1": 51123,
      "dead_t2": 3572,
      "dead_t3": 878,
      "dead_t4": 278738,
      "dead_t5": 799547
    },
    {
      "id": "33697867",
      "name": "서민공돌이",
      "max_power": 103649530,
      "power": 96796979,
      "collect": 1669304711,
      "dead": 1184873,
      "kill": 861008097,
      "t1": 18505,
      "t2": 60819,
      "t3": 180337,
      "t4": 5617767,
      "t5": 40199187,
      "help": 3570,
      "dt": "2026/03/06",
      "dead_t1": 0,
      "dead_t2": 0,
      "dead_t3": 0,
      "dead_t4": 0,
      "dead_t5": 925988
    },
    {
      "id": "34861519",
      "name": "망      치",
      "max_power": 113885570,
      "power": 94792682,
      "collect": 772407796,
      "dead": 1486227,
      "kill": 861360601,
      "t1": 199375,
      "t2": 177238,
      "t3": 1630,
      "t4": 8835175,
      "t5": 38630399,
      "help": 3750,
      "dt": "2026/03/06",
      "dead_t1": 0,
      "dead_t2": 0,
      "dead_t3": 0,
      "dead_t4": 7225,
      "dead_t5": 961826
    },
    {
      "id": "37656208",
      "name": "채집3대",
      "max_power": 112954773,
      "power": 93000177,
      "collect": 1907595519,
      "dead": 5906836,
      "kill": 800252828,
      "t1": 229577,
      "t2": 67302,
      "t3": 16067,
      "t4": 6154536,
      "t5": 36923134,
      "help": 8021,
      "dt": "2026/03/06",
      "dead_t1": 383952,
      "dead_t2": 244426,
      "dead_t3": 7482,
      "dead_t4": 92795,
      "dead_t5": 4422561
    },
    {
      "id": "31666791",
      "name": "Soboru",
      "max_power": 130013219,
      "power": 91534423,
      "collect": 1776696797,
      "dead": 3007199,
      "kill": 2388648486,
      "t1": 264988,
      "t2": 348572,
      "t3": 181066,
      "t4": 16452994,
      "t5": 111132207,
      "help": 4792,
      "dt": "2026/03/06",
      "dead_t1": 0,
      "dead_t2": 0,
      "dead_t3": 0,
      "dead_t4": 0,
      "dead_t5": 1927480
    },
    {
      "id": "44490294",
      "name": "o0oBeoo0o",
      "max_power": 103630750,
      "power": 88390528,
      "collect": 3003725635,
      "dead": 3601824,
      "kill": 397636532,
      "t1": 2047883,
      "t2": 170466,
      "t3": 222206,
      "t4": 8796142,
      "t5": 15401789,
      "help": 1939,
      "dt": "2026/03/06",
      "dead_t1": 81152,
      "dead_t2": 0,
      "dead_t3": 0,
      "dead_t4": 589981,
      "dead_t5": 2125583
    },
    {
      "id": "53530629",
      "name": "준     이",
      "max_power": 138397741,
      "power": 82593093,
      "collect": 1927858142,
      "dead": 38016,
      "kill": 3047540,
      "t1": 0,
      "t2": 0,
      "t3": 0,
      "t4": 18996,
      "t5": 142879,
      "help": 736,
      "dt": "2026/03/06",
      "dead_t1": 0,
      "dead_t2": 0,
      "dead_t3": 0,
      "dead_t4": 0,
      "dead_t5": 38016
    },
    {
      "id": "49292250",
      "name": "皇M㋡㋡N皇",
      "max_power": 111275708,
      "power": 78897443,
      "collect": 78354017,
      "dead": 5877182,
      "kill": 128988086,
      "t1": 95669,
      "t2": 5016,
      "t3": 0,
      "t4": 1047700,
      "t5": 5924096,
      "help": 27009,
      "dt": "2026/03/06",
      "dead_t1": 69127,
      "dead_t2": 2000,
      "dead_t3": 0,
      "dead_t4": 2203290,
      "dead_t5": 2609205
    },
    {
      "id": "76993611",
      "name": "e33sxfopp",
      "max_power": 69070367,
      "power": 65238780,
      "collect": 1205133002,
      "dead": 998222,
      "kill": 16427510,
      "t1": 0,
      "t2": 0,
      "t3": 0,
      "t4": 171991,
      "t5": 735380,
      "help": 81,
      "dt": "2026/03/06",
      "dead_t1": 0,
      "dead_t2": 0,
      "dead_t3": 0,
      "dead_t4": 0,
      "dead_t5": 998222
    },
    {
      "id": "90971922",
      "name": "ZenithRaver",
      "max_power": 62359963,
      "power": 61726686,
      "collect": 912790096,
      "dead": 4964644,
      "kill": 167431886,
      "t1": 154340,
      "t2": 357156,
      "t3": 29389,
      "t4": 2088625,
      "t5": 7284145,
      "help": 2567,
      "dt": "2026/03/06",
      "dead_t1": 9119,
      "dead_t2": 307,
      "dead_t3": 0,
      "dead_t4": 1758036,
      "dead_t5": 246269
    },
    {
      "id": "31648737",
      "name": "Stering",
      "max_power": 110074351,
      "power": 56019017,
      "collect": 0,
      "dead": 0,
      "kill": 0,
      "t1": 0,
      "t2": 0,
      "t3": 0,
      "t4": 0,
      "t5": 0,
      "help": 0,
      "dt": "2026/03/06",
      "dead_t1": 0,
      "dead_t2": 0,
      "dead_t3": 0,
      "dead_t4": 0,
      "dead_t5": 0
    },
    {
      "id": "145849032",
      "name": "꽐라레이스",
      "max_power": 53153156,
      "power": 53151196,
      "collect": 5690832230,
      "dead": 350046,
      "kill": 4736540,
      "t1": 1,
      "t2": 0,
      "t3": 0,
      "t4": 42610,
      "t5": 215522,
      "help": 1062,
      "dt": "2026/03/06",
      "dead_t1": 0,
      "dead_t2": 0,
      "dead_t3": 0,
      "dead_t4": 350046,
      "dead_t5": 0
    },
    {
      "id": "35103666",
      "name": "황 뚝",
      "max_power": 49201726,
      "power": 45663774,
      "collect": 1303709216,
      "dead": 1792202,
      "kill": 68241006,
      "t1": 1601272,
      "t2": 1817696,
      "t3": 1149965,
      "t4": 3593030,
      "t5": 1187760,
      "help": 542,
      "dt": "2026/03/06",
      "dead_t1": 0,
      "dead_t2": 0,
      "dead_t3": 0,
      "dead_t4": 1253520,
      "dead_t5": 0
    },
    {
      "id": "161493600",
      "name": "소맥레이스",
      "max_power": 42361416,
      "power": 40249291,
      "collect": 5775588842,
      "dead": 3476459,
      "kill": 8871750,
      "t1": 1,
      "t2": 0,
      "t3": 0,
      "t4": 49209,
      "t5": 418983,
      "help": 1226,
      "dt": "2026/03/06",
      "dead_t1": 0,
      "dead_t2": 0,
      "dead_t3": 0,
      "dead_t4": 252252,
      "dead_t5": 0
    },
    {
      "id": "36520198",
      "name": "망치의 쌀",
      "max_power": 48352779,
      "power": 38892492,
      "collect": 658473267,
      "dead": 106757,
      "kill": 934221,
      "t1": 7,
      "t2": 0,
      "t3": 0,
      "t4": 820,
      "t5": 46301,
      "help": 154,
      "dt": "2026/03/06",
      "dead_t1": 471,
      "dead_t2": 0,
      "dead_t3": 0,
      "dead_t4": 106286,
      "dead_t5": 0
    },
    {
      "id": "176230632",
      "name": "sonny7 부캐8",
      "max_power": 38075977,
      "power": 38075977,
      "collect": 1499760513,
      "dead": 1220591,
      "kill": 38225085,
      "t1": 71185,
      "t2": 46731,
      "t3": 10899,
      "t4": 566491,
      "t5": 1620444,
      "help": 1492,
      "dt": "2026/03/06",
      "dead_t1": 213,
      "dead_t2": 0,
      "dead_t3": 0,
      "dead_t4": 906612,
      "dead_t5": 0
    },
    {
      "id": "174873009",
      "name": "sonny7 부캐7",
      "max_power": 37460426,
      "power": 37460426,
      "collect": 1597239888,
      "dead": 3063944,
      "kill": 47730751,
      "t1": 102782,
      "t2": 44527,
      "t3": 9715,
      "t4": 701946,
      "t5": 2028141,
      "help": 1489,
      "dt": "2026/03/06",
      "dead_t1": 0,
      "dead_t2": 0,
      "dead_t3": 0,
      "dead_t4": 888233,
      "dead_t5": 0
    },
    {
      "id": "174844484",
      "name": "ᴸᴱsonny7부캐6",
      "max_power": 37595175,
      "power": 36819180,
      "collect": 1701608876,
      "dead": 4140013,
      "kill": 44026329,
      "t1": 66985,
      "t2": 32897,
      "t3": 10182,
      "t4": 698081,
      "t5": 1846280,
      "help": 1592,
      "dt": "2026/03/06",
      "dead_t1": 749,
      "dead_t2": 0,
      "dead_t3": 0,
      "dead_t4": 2292564,
      "dead_t5": 0
    },
    {
      "id": "40777278",
      "name": "망치의 목재",
      "max_power": 41177770,
      "power": 33400014,
      "collect": 688969855,
      "dead": 6818,
      "kill": 108950,
      "t1": 2,
      "t2": 0,
      "t3": 0,
      "t4": 2281,
      "t5": 4307,
      "help": 157,
      "dt": "2026/03/06",
      "dead_t1": 1813,
      "dead_t2": 0,
      "dead_t3": 0,
      "dead_t4": 5005,
      "dead_t5": 0
    },
    {
      "id": "90783853",
      "name": "채집4대",
      "max_power": 33012659,
      "power": 33007191,
      "collect": 1457288198,
      "dead": 222681,
      "kill": 7903147,
      "t1": 10225,
      "t2": 2960,
      "t3": 1553,
      "t4": 122379,
      "t5": 333259,
      "help": 756,
      "dt": "2026/03/06",
      "dead_t1": 0,
      "dead_t2": 0,
      "dead_t3": 0,
      "dead_t4": 0,
      "dead_t5": 0
    },
    {
      "id": "84411596",
      "name": "채집 1대",
      "max_power": 33085273,
      "power": 32778161,
      "collect": 1229155227,
      "dead": 454325,
      "kill": 8699078,
      "t1": 60,
      "t2": 49,
      "t3": 57,
      "t4": 72288,
      "t5": 398793,
      "help": 473,
      "dt": "2026/03/06",
      "dead_t1": 0,
      "dead_t2": 0,
      "dead_t3": 0,
      "dead_t4": 0,
      "dead_t5": 0
    },
    {
      "id": "59288248",
      "name": "소탱이 5",
      "max_power": 32815026,
      "power": 30317257,
      "collect": 1488439530,
      "dead": 1215838,
      "kill": 3680160,
      "t1": 1,
      "t2": 0,
      "t3": 0,
      "t4": 16694,
      "t5": 175661,
      "help": 636,
      "dt": "2026/03/06",
      "dead_t1": 48473,
      "dead_t2": 86234,
      "dead_t3": 1111,
      "dead_t4": 993249,
      "dead_t5": 0
    },
    {
      "id": "92570572",
      "name": "서민공돌4",
      "max_power": 30824145,
      "power": 29236295,
      "collect": 1183498030,
      "dead": 485307,
      "kill": 9385392,
      "t1": 130,
      "t2": 235,
      "t3": 174,
      "t4": 175296,
      "t5": 381562,
      "help": 286,
      "dt": "2026/03/06",
      "dead_t1": 0,
      "dead_t2": 0,
      "dead_t3": 0,
      "dead_t4": 469284,
      "dead_t5": 0
    },
    {
      "id": "130400149",
      "name": "황뚝2",
      "max_power": 29358312,
      "power": 29210904,
      "collect": 852020293,
      "dead": 1448391,
      "kill": 29899245,
      "t1": 357556,
      "t2": 790940,
      "t3": 490896,
      "t4": 494477,
      "t5": 1066875,
      "help": 226,
      "dt": "2026/03/06",
      "dead_t1": 0,
      "dead_t2": 0,
      "dead_t3": 0,
      "dead_t4": 851859,
      "dead_t5": 0
    },
    {
      "id": "130403838",
      "name": "황뚝1",
      "max_power": 31629482,
      "power": 29171021,
      "collect": 1170493951,
      "dead": 1863475,
      "kill": 45605224,
      "t1": 294398,
      "t2": 257966,
      "t3": 966363,
      "t4": 1838636,
      "t5": 1138930,
      "help": 308,
      "dt": "2026/03/06",
      "dead_t1": 0,
      "dead_t2": 0,
      "dead_t3": 0,
      "dead_t4": 929370,
      "dead_t5": 0
    },
    {
      "id": "95842609",
      "name": "Turan Elı",
      "max_power": 30366060,
      "power": 28849672,
      "collect": 509390063,
      "dead": 1181665,
      "kill": 1463880,
      "t1": 0,
      "t2": 0,
      "t3": 0,
      "t4": 40510,
      "t5": 52939,
      "help": 125,
      "dt": "2026/03/06",
      "dead_t1": 0,
      "dead_t2": 505,
      "dead_t3": 1310,
      "dead_t4": 1012001,
      "dead_t5": 0
    },
    {
      "id": "89684154",
      "name": "이빠잉4",
      "max_power": 34172849,
      "power": 28825836,
      "collect": 3346730391,
      "dead": 757754,
      "kill": 23652879,
      "t1": 30003,
      "t2": 31787,
      "t3": 326,
      "t4": 246616,
      "t5": 1055792,
      "help": 1717,
      "dt": "2026/03/06",
      "dead_t1": 5,
      "dead_t2": 0,
      "dead_t3": 0,
      "dead_t4": 757749,
      "dead_t5": 0
    },
    {
      "id": "91113224",
      "name": "서민공돌3",
      "max_power": 31424084,
      "power": 28774301,
      "collect": 1118248586,
      "dead": 1038709,
      "kill": 15514173,
      "t1": 2687,
      "t2": 454,
      "t3": 57,
      "t4": 307568,
      "t5": 621841,
      "help": 356,
      "dt": "2026/03/06",
      "dead_t1": 0,
      "dead_t2": 0,
      "dead_t3": 0,
      "dead_t4": 428072,
      "dead_t5": 0
    },
    {
      "id": "50712339",
      "name": "호나우도1",
      "max_power": 28648552,
      "power": 28640252,
      "collect": 1781431498,
      "dead": 320682,
      "kill": 4546845,
      "t1": 6712,
      "t2": 11,
      "t3": 0,
      "t4": 86118,
      "t5": 184215,
      "help": 533,
      "dt": "2026/03/06",
      "dead_t1": 0,
      "dead_t2": 0,
      "dead_t3": 0,
      "dead_t4": 0,
      "dead_t5": 0
    },
    {
      "id": "46922472",
      "name": "호나우도2",
      "max_power": 29010531,
      "power": 28481957,
      "collect": 1792374926,
      "dead": 1058549,
      "kill": 2894340,
      "t1": 5848,
      "t2": 0,
      "t3": 0,
      "t4": 33331,
      "t5": 127993,
      "help": 512,
      "dt": "2026/03/06",
      "dead_t1": 0,
      "dead_t2": 0,
      "dead_t3": 0,
      "dead_t4": 0,
      "dead_t5": 0
    },
    {
      "id": "142835768",
      "name": "서민공돌5",
      "max_power": 29056278,
      "power": 28390990,
      "collect": 1086377852,
      "dead": 908454,
      "kill": 13014579,
      "t1": 215,
      "t2": 441,
      "t3": 551,
      "t4": 301579,
      "t5": 499783,
      "help": 297,
      "dt": "2026/03/06",
      "dead_t1": 0,
      "dead_t2": 0,
      "dead_t3": 0,
      "dead_t4": 424446,
      "dead_t5": 0
    },
    {
      "id": "46098963",
      "name": "고 독 팀 A1",
      "max_power": 44991526,
      "power": 28001286,
      "collect": 2224611980,
      "dead": 0,
      "kill": 0,
      "t1": 0,
      "t2": 0,
      "t3": 0,
      "t4": 0,
      "t5": 0,
      "help": 1,
      "dt": "2026/03/06",
      "dead_t1": 0,
      "dead_t2": 0,
      "dead_t3": 0,
      "dead_t4": 0,
      "dead_t5": 0
    },
    {
      "id": "177546180",
      "name": "ᴷᴬ이빠잉义",
      "max_power": 31938621,
      "power": 27926687,
      "collect": 3008423352,
      "dead": 548996,
      "kill": 23273451,
      "t1": 47433,
      "t2": 28775,
      "t3": 206,
      "t4": 228619,
      "t5": 1045970,
      "help": 1674,
      "dt": "2026/03/06",
      "dead_t1": 520,
      "dead_t2": 0,
      "dead_t3": 0,
      "dead_t4": 548476,
      "dead_t5": 0
    },
    {
      "id": "32498499",
      "name": "도박치료1",
      "max_power": 27600209,
      "power": 27600209,
      "collect": 4634901107,
      "dead": 1207616,
      "kill": 26680255,
      "t1": 64,
      "t2": 28883,
      "t3": 1349,
      "t4": 579156,
      "t5": 1041276,
      "help": 359,
      "dt": "2026/03/06",
      "dead_t1": 0,
      "dead_t2": 0,
      "dead_t3": 0,
      "dead_t4": 448328,
      "dead_t5": 0
    },
    {
      "id": "42004215",
      "name": "황뚝4",
      "max_power": 29971986,
      "power": 27269332,
      "collect": 833403021,
      "dead": 3035528,
      "kill": 49379403,
      "t1": 50895,
      "t2": 3484,
      "t3": 34,
      "t4": 714378,
      "t5": 2110917,
      "help": 191,
      "dt": "2026/03/06",
      "dead_t1": 0,
      "dead_t2": 0,
      "dead_t3": 0,
      "dead_t4": 1490313,
      "dead_t5": 0
    },
    {
      "id": "182379015",
      "name": "소탱이 8",
      "max_power": 27101481,
      "power": 27099569,
      "collect": 1168105529,
      "dead": 50214,
      "kill": 215510,
      "t1": 0,
      "t2": 0,
      "t3": 0,
      "t4": 3889,
      "t5": 8831,
      "help": 532,
      "dt": "2026/03/06",
      "dead_t1": 0,
      "dead_t2": 0,
      "dead_t3": 0,
      "dead_t4": 50214,
      "dead_t5": 0
    },
    {
      "id": "59285611",
      "name": "소탱이 7",
      "max_power": 29128726,
      "power": 27032166,
      "collect": 1236567676,
      "dead": 1611001,
      "kill": 2788750,
      "t1": 0,
      "t2": 0,
      "t3": 0,
      "t4": 5771,
      "t5": 136552,
      "help": 639,
      "dt": "2026/03/06",
      "dead_t1": 48210,
      "dead_t2": 148170,
      "dead_t3": 38528,
      "dead_t4": 1277204,
      "dead_t5": 0
    },
    {
      "id": "144915686",
      "name": "채집6대",
      "max_power": 26513217,
      "power": 26504573,
      "collect": 1359744631,
      "dead": 293204,
      "kill": 7221528,
      "t1": 140,
      "t2": 0,
      "t3": 0,
      "t4": 251770,
      "t5": 235190,
      "help": 574,
      "dt": "2026/03/06",
      "dead_t1": 0,
      "dead_t2": 0,
      "dead_t3": 0,
      "dead_t4": 0,
      "dead_t5": 0
    },
    {
      "id": "166470061",
      "name": "도박치료5",
      "max_power": 25936586,
      "power": 25936586,
      "collect": 4505864935,
      "dead": 493673,
      "kill": 7092291,
      "t1": 2356,
      "t2": 0,
      "t3": 0,
      "t4": 147702,
      "t5": 280740,
      "help": 265,
      "dt": "2026/03/06",
      "dead_t1": 0,
      "dead_t2": 0,
      "dead_t3": 0,
      "dead_t4": 282542,
      "dead_t5": 0
    },
    {
      "id": "48400866",
      "name": "V Quỷ ĐỏII",
      "max_power": 33551872,
      "power": 25872949,
      "collect": 4165660468,
      "dead": 0,
      "kill": 862150,
      "t1": 0,
      "t2": 0,
      "t3": 0,
      "t4": 1043,
      "t5": 42586,
      "help": 1017,
      "dt": "2026/03/06",
      "dead_t1": 0,
      "dead_t2": 0,
      "dead_t3": 0,
      "dead_t4": 0,
      "dead_t5": 0
    },
    {
      "id": "167683392",
      "name": "황뚝3",
      "max_power": 27116145,
      "power": 25674234,
      "collect": 826093308,
      "dead": 1845752,
      "kill": 33813927,
      "t1": 429275,
      "t2": 29666,
      "t3": 900,
      "t4": 553388,
      "t5": 1406563,
      "help": 196,
      "dt": "2026/03/06",
      "dead_t1": 0,
      "dead_t2": 0,
      "dead_t3": 0,
      "dead_t4": 1098115,
      "dead_t5": 0
    },
    {
      "id": "166469719",
      "name": "도박치료4",
      "max_power": 25577924,
      "power": 25577924,
      "collect": 4576912602,
      "dead": 411635,
      "kill": 7823921,
      "t1": 51,
      "t2": 0,
      "t3": 0,
      "t4": 153077,
      "t5": 314657,
      "help": 227,
      "dt": "2026/03/06",
      "dead_t1": 0,
      "dead_t2": 0,
      "dead_t3": 0,
      "dead_t4": 225764,
      "dead_t5": 0
    },
    {
      "id": "41552181",
      "name": "도박치료3",
      "max_power": 25450954,
      "power": 25450954,
      "collect": 4645242303,
      "dead": 437148,
      "kill": 7635312,
      "t1": 1,
      "t2": 4301,
      "t3": 0,
      "t4": 158173,
      "t5": 302249,
      "help": 281,
      "dt": "2026/03/06",
      "dead_t1": 0,
      "dead_t2": 0,
      "dead_t3": 0,
      "dead_t4": 180891,
      "dead_t5": 0
    },
    {
      "id": "84411152",
      "name": "채집 2대",
      "max_power": 25327521,
      "power": 25319745,
      "collect": 1206352693,
      "dead": 80237,
      "kill": 6024406,
      "t1": 23960,
      "t2": 3257,
      "t3": 0,
      "t4": 74926,
      "t5": 263192,
      "help": 441,
      "dt": "2026/03/06",
      "dead_t1": 0,
      "dead_t2": 0,
      "dead_t3": 0,
      "dead_t4": 80237,
      "dead_t5": 0
    },
    {
      "id": "35274285",
      "name": "도박치료2",
      "max_power": 25246098,
      "power": 25246098,
      "collect": 4623503957,
      "dead": 943484,
      "kill": 22844773,
      "t1": 36,
      "t2": 17875,
      "t3": 269,
      "t4": 412650,
      "t5": 934072,
      "help": 343,
      "dt": "2026/03/06",
      "dead_t1": 0,
      "dead_t2": 0,
      "dead_t3": 0,
      "dead_t4": 379044,
      "dead_t5": 0
    },
    {
      "id": "182457540",
      "name": "소탱이 1",
      "max_power": 27522187,
      "power": 25182903,
      "collect": 1197547316,
      "dead": 1603971,
      "kill": 2362000,
      "t1": 0,
      "t2": 0,
      "t3": 0,
      "t4": 0,
      "t5": 118100,
      "help": 621,
      "dt": "2026/03/06",
      "dead_t1": 0,
      "dead_t2": 162879,
      "dead_t3": 132647,
      "dead_t4": 1308445,
      "dead_t5": 0
    },
    {
      "id": "197196172",
      "name": "채집 4대",
      "max_power": 24981971,
      "power": 24981971,
      "collect": 1948871207,
      "dead": 0,
      "kill": 0,
      "t1": 0,
      "t2": 0,
      "t3": 0,
      "t4": 0,
      "t5": 0,
      "help": 744,
      "dt": "2026/03/06",
      "dead_t1": 0,
      "dead_t2": 0,
      "dead_t3": 0,
      "dead_t4": 0,
      "dead_t5": 0
    },
    {
      "id": "65543977",
      "name": "V Quỷ Đỏ I",
      "max_power": 33397918,
      "power": 24427475,
      "collect": 4351125542,
      "dead": 1600464,
      "kill": 1871070,
      "t1": 1,
      "t2": 0,
      "t3": 0,
      "t4": 24893,
      "t5": 81107,
      "help": 1046,
      "dt": "2026/03/06",
      "dead_t1": 0,
      "dead_t2": 0,
      "dead_t3": 0,
      "dead_t4": 0,
      "dead_t5": 0
    },
    {
      "id": "66493495",
      "name": "강하다IK",
      "max_power": 23235546,
      "power": 23205946,
      "collect": 828681127,
      "dead": 0,
      "kill": 0,
      "t1": 0,
      "t2": 0,
      "t3": 0,
      "t4": 0,
      "t5": 0,
      "help": 134,
      "dt": "2026/03/06",
      "dead_t1": 0,
      "dead_t2": 0,
      "dead_t3": 0,
      "dead_t4": 0,
      "dead_t5": 0
    },
    {
      "id": "114276478",
      "name": "V QuỷĐỏ 3",
      "max_power": 25656361,
      "power": 22754242,
      "collect": 2571247257,
      "dead": 2445736,
      "kill": 6140911,
      "t1": 3856,
      "t2": 1905,
      "t3": 0,
      "t4": 71489,
      "t5": 271072,
      "help": 840,
      "dt": "2026/03/06",
      "dead_t1": 0,
      "dead_t2": 0,
      "dead_t3": 0,
      "dead_t4": 22634,
      "dead_t5": 0
    },
    {
      "id": "182375308",
      "name": "소탱이 9",
      "max_power": 22576451,
      "power": 22576451,
      "collect": 2023538543,
      "dead": 0,
      "kill": 78730,
      "t1": 0,
      "t2": 0,
      "t3": 0,
      "t4": 937,
      "t5": 3468,
      "help": 966,
      "dt": "2026/03/06",
      "dead_t1": 0,
      "dead_t2": 0,
      "dead_t3": 0,
      "dead_t4": 0,
      "dead_t5": 0
    },
    {
      "id": "53532897",
      "name": "고 독 팀 A2",
      "max_power": 38237510,
      "power": 22547400,
      "collect": 1922701189,
      "dead": 0,
      "kill": 0,
      "t1": 0,
      "t2": 0,
      "t3": 0,
      "t4": 0,
      "t5": 0,
      "help": 1,
      "dt": "2026/03/06",
      "dead_t1": 0,
      "dead_t2": 0,
      "dead_t3": 0,
      "dead_t4": 0,
      "dead_t5": 0
    },
    {
      "id": "89159968",
      "name": "Quỷ Đỏ VI",
      "max_power": 23193661,
      "power": 22136992,
      "collect": 3625676167,
      "dead": 24241,
      "kill": 881077,
      "t1": 3176,
      "t2": 126,
      "t3": 0,
      "t4": 711,
      "t5": 43654,
      "help": 919,
      "dt": "2026/03/06",
      "dead_t1": 0,
      "dead_t2": 0,
      "dead_t3": 0,
      "dead_t4": 24241,
      "dead_t5": 0
    },
    {
      "id": "105541174",
      "name": "Beo nè",
      "max_power": 24944953,
      "power": 21774401,
      "collect": 492835644,
      "dead": 1852763,
      "kill": 10052161,
      "t1": 27,
      "t2": 108,
      "t3": 0,
      "t4": 182998,
      "t5": 411098,
      "help": 124,
      "dt": "2026/03/06",
      "dead_t1": 0,
      "dead_t2": 0,
      "dead_t3": 0,
      "dead_t4": 0,
      "dead_t5": 0
    },
    {
      "id": "175814182",
      "name": "황뚝5",
      "max_power": 20691656,
      "power": 20691656,
      "collect": 703871577,
      "dead": 1082899,
      "kill": 18539428,
      "t1": 33248,
      "t2": 1604,
      "t3": 735,
      "t4": 271431,
      "t5": 790616,
      "help": 180,
      "dt": "2026/03/06",
      "dead_t1": 50,
      "dead_t2": 0,
      "dead_t3": 0,
      "dead_t4": 529578,
      "dead_t5": 0
    },
    {
      "id": "175813929",
      "name": "황뚝6",
      "max_power": 20605149,
      "power": 20313852,
      "collect": 652505452,
      "dead": 1078429,
      "kill": 19271612,
      "t1": 46190,
      "t2": 1135,
      "t3": 1186,
      "t4": 214270,
      "t5": 855633,
      "help": 182,
      "dt": "2026/03/06",
      "dead_t1": 7136,
      "dead_t2": 0,
      "dead_t3": 0,
      "dead_t4": 675461,
      "dead_t5": 0
    },
    {
      "id": "41436786",
      "name": "망치 쌀알",
      "max_power": 18916210,
      "power": 18916210,
      "collect": 597664086,
      "dead": 23464,
      "kill": 468761,
      "t1": 7,
      "t2": 0,
      "t3": 0,
      "t4": 10066,
      "t5": 18405,
      "help": 169,
      "dt": "2026/03/06",
      "dead_t1": 0,
      "dead_t2": 0,
      "dead_t3": 0,
      "dead_t4": 23464,
      "dead_t5": 0
    },
    {
      "id": "58680851",
      "name": "Sugar Mrjun far",
      "max_power": 31019086,
      "power": 18723682,
      "collect": 250673858,
      "dead": 0,
      "kill": 3140,
      "t1": 0,
      "t2": 0,
      "t3": 0,
      "t4": 0,
      "t5": 157,
      "help": 19,
      "dt": "2026/03/06",
      "dead_t1": 0,
      "dead_t2": 0,
      "dead_t3": 0,
      "dead_t4": 0,
      "dead_t5": 0
    },
    {
      "id": "46123107",
      "name": "고 독 팀 A3",
      "max_power": 31956235,
      "power": 18182471,
      "collect": 1767866563,
      "dead": 0,
      "kill": 0,
      "t1": 0,
      "t2": 0,
      "t3": 0,
      "t4": 0,
      "t5": 0,
      "help": 1,
      "dt": "2026/03/06",
      "dead_t1": 0,
      "dead_t2": 0,
      "dead_t3": 0,
      "dead_t4": 0,
      "dead_t5": 0
    },
    {
      "id": "68509463",
      "name": "호나우도",
      "max_power": 17996190,
      "power": 17996190,
      "collect": 1065651700,
      "dead": 0,
      "kill": 0,
      "t1": 0,
      "t2": 0,
      "t3": 0,
      "t4": 0,
      "t5": 0,
      "help": 294,
      "dt": "2026/03/06",
      "dead_t1": 0,
      "dead_t2": 0,
      "dead_t3": 0,
      "dead_t4": 0,
      "dead_t5": 0
    },
    {
      "id": "173626259",
      "name": "서민공돌7",
      "max_power": 15946774,
      "power": 15946774,
      "collect": 669230100,
      "dead": 0,
      "kill": 0,
      "t1": 0,
      "t2": 0,
      "t3": 0,
      "t4": 0,
      "t5": 0,
      "help": 35,
      "dt": "2026/03/06",
      "dead_t1": 0,
      "dead_t2": 0,
      "dead_t3": 0,
      "dead_t4": 0,
      "dead_t5": 0
    },
    {
      "id": "163565221",
      "name": "서민공돌6",
      "max_power": 15943758,
      "power": 15943758,
      "collect": 658770000,
      "dead": 0,
      "kill": 0,
      "t1": 0,
      "t2": 0,
      "t3": 0,
      "t4": 0,
      "t5": 0,
      "help": 33,
      "dt": "2026/03/06",
      "dead_t1": 0,
      "dead_t2": 0,
      "dead_t3": 0,
      "dead_t4": 0,
      "dead_t5": 0
    },
    {
      "id": "79486785",
      "name": "F3k",
      "max_power": 22186420,
      "power": 15319224,
      "collect": 48846000,
      "dead": 2295251,
      "kill": 1690020,
      "t1": 0,
      "t2": 0,
      "t3": 0,
      "t4": 0,
      "t5": 84501,
      "help": 0,
      "dt": "2026/03/06",
      "dead_t1": 14545,
      "dead_t2": 8,
      "dead_t3": 0,
      "dead_t4": 55410,
      "dead_t5": 0
    },
    {
      "id": "37106943",
      "name": "채집 3대",
      "max_power": 14859336,
      "power": 14857628,
      "collect": 1568168643,
      "dead": 0,
      "kill": 0,
      "t1": 0,
      "t2": 0,
      "t3": 0,
      "t4": 0,
      "t5": 0,
      "help": 598,
      "dt": "2026/03/06",
      "dead_t1": 0,
      "dead_t2": 0,
      "dead_t3": 0,
      "dead_t4": 0,
      "dead_t5": 0
    },
    {
      "id": "62606963",
      "name": "Soboru farm 4",
      "max_power": 17713111,
      "power": 14100952,
      "collect": 52316405,
      "dead": 100722,
      "kill": 2853435,
      "t1": 2356,
      "t2": 3455,
      "t3": 191,
      "t4": 86903,
      "t5": 98813,
      "help": 137,
      "dt": "2026/03/06",
      "dead_t1": 0,
      "dead_t2": 0,
      "dead_t3": 0,
      "dead_t4": 100722,
      "dead_t5": 0
    },
    {
      "id": "32676942",
      "name": "Soboru farm 5",
      "max_power": 17911514,
      "power": 13325915,
      "collect": 14952700,
      "dead": 55046,
      "kill": 1553282,
      "t1": 4793,
      "t2": 27479,
      "t3": 19344,
      "t4": 56379,
      "t5": 42810,
      "help": 5,
      "dt": "2026/03/06",
      "dead_t1": 0,
      "dead_t2": 0,
      "dead_t3": 0,
      "dead_t4": 55046,
      "dead_t5": 0
    },
    {
      "id": "167432658",
      "name": "Quỷ Đỏ V",
      "max_power": 13169795,
      "power": 13169795,
      "collect": 775070440,
      "dead": 0,
      "kill": 0,
      "t1": 0,
      "t2": 0,
      "t3": 0,
      "t4": 0,
      "t5": 0,
      "help": 405,
      "dt": "2026/03/06",
      "dead_t1": 0,
      "dead_t2": 0,
      "dead_t3": 0,
      "dead_t4": 0,
      "dead_t5": 0
    },
    {
      "id": "86697527",
      "name": "F4k",
      "max_power": 19829952,
      "power": 13132696,
      "collect": 60637500,
      "dead": 1295120,
      "kill": 1534420,
      "t1": 0,
      "t2": 0,
      "t3": 0,
      "t4": 146910,
      "t5": 3266,
      "help": 1,
      "dt": "2026/03/06",
      "dead_t1": 321515,
      "dead_t2": 40996,
      "dead_t3": 0,
      "dead_t4": 932609,
      "dead_t5": 0
    },
    {
      "id": "58701581",
      "name": "الإنفجار",
      "max_power": 12632931,
      "power": 12632931,
      "collect": 600511123,
      "dead": 0,
      "kill": 0,
      "t1": 0,
      "t2": 0,
      "t3": 0,
      "t4": 0,
      "t5": 0,
      "help": 41,
      "dt": "2026/03/06",
      "dead_t1": 0,
      "dead_t2": 0,
      "dead_t3": 0,
      "dead_t4": 0,
      "dead_t5": 0
    },
    {
      "id": "79931237",
      "name": "F6k",
      "max_power": 13949372,
      "power": 11626276,
      "collect": 38994375,
      "dead": 793547,
      "kill": 274430,
      "t1": 0,
      "t2": 0,
      "t3": 0,
      "t4": 1823,
      "t5": 12810,
      "help": 2,
      "dt": "2026/03/06",
      "dead_t1": 0,
      "dead_t2": 1071,
      "dead_t3": 10101,
      "dead_t4": 4685,
      "dead_t5": 0
    },
    {
      "id": "54659907",
      "name": "손 생님 230",
      "max_power": 9788635,
      "power": 9788635,
      "collect": 149902035,
      "dead": 350254,
      "kill": 138870,
      "t1": 0,
      "t2": 0,
      "t3": 0,
      "t4": 1601,
      "t5": 6143,
      "help": 9,
      "dt": "2026/03/06",
      "dead_t1": 0,
      "dead_t2": 0,
      "dead_t3": 0,
      "dead_t4": 0,
      "dead_t5": 0
    },
    {
      "id": "95791654",
      "name": "Wilhelminaaas",
      "max_power": 9628963,
      "power": 8747180,
      "collect": 618965064,
      "dead": 537897,
      "kill": 583730,
      "t1": 0,
      "t2": 0,
      "t3": 0,
      "t4": 58373,
      "t5": 0,
      "help": 124,
      "dt": "2026/03/06",
      "dead_t1": 0,
      "dead_t2": 0,
      "dead_t3": 36993,
      "dead_t4": 249312,
      "dead_t5": 0
    },
    {
      "id": "95798578",
      "name": "арно",
      "max_power": 6537358,
      "power": 6033613,
      "collect": 6567408,
      "dead": 0,
      "kill": 172180,
      "t1": 0,
      "t2": 0,
      "t3": 0,
      "t4": 17218,
      "t5": 0,
      "help": 62,
      "dt": "2026/03/06",
      "dead_t1": 0,
      "dead_t2": 0,
      "dead_t3": 0,
      "dead_t4": 0,
      "dead_t5": 0
    },
    {
      "id": "95850827",
      "name": "傑克森傑森",
      "max_power": 5519347,
      "power": 5095947,
      "collect": 0,
      "dead": 13494,
      "kill": 206920,
      "t1": 0,
      "t2": 0,
      "t3": 0,
      "t4": 20692,
      "t5": 0,
      "help": 43,
      "dt": "2026/03/06",
      "dead_t1": 0,
      "dead_t2": 0,
      "dead_t3": 0,
      "dead_t4": 13494,
      "dead_t5": 0
    },
    {
      "id": "153439460",
      "name": "Goku Farm 10",
      "max_power": 2612895,
      "power": 2205443,
      "collect": 0,
      "dead": 48269,
      "kill": 85170,
      "t1": 0,
      "t2": 0,
      "t3": 0,
      "t4": 8517,
      "t5": 0,
      "help": 8,
      "dt": "2026/03/06",
      "dead_t1": 1700,
      "dead_t2": 29642,
      "dead_t3": 16927,
      "dead_t4": 0,
      "dead_t5": 0
    },
    {
      "id": "154904967",
      "name": "HENDRA 14",
      "max_power": 2764675,
      "power": 1761813,
      "collect": 0,
      "dead": 33195,
      "kill": 46690,
      "t1": 0,
      "t2": 0,
      "t3": 0,
      "t4": 4669,
      "t5": 0,
      "help": 9,
      "dt": "2026/03/06",
      "dead_t1": 3988,
      "dead_t2": 6606,
      "dead_t3": 22601,
      "dead_t4": 0,
      "dead_t5": 0
    },
    {
      "id": "95760277",
      "name": "Ализмон",
      "max_power": 598941,
      "power": 558673,
      "collect": 326405,
      "dead": 0,
      "kill": 2020,
      "t1": 0,
      "t2": 0,
      "t3": 0,
      "t4": 202,
      "t5": 0,
      "help": 0,
      "dt": "2026/03/06",
      "dead_t1": 0,
      "dead_t2": 0,
      "dead_t3": 0,
      "dead_t4": 0,
      "dead_t5": 0
    },
    {
      "id": "209504572",
      "name": "Governor209504572",
      "max_power": 42201,
      "power": 42201,
      "collect": 0,
      "dead": 0,
      "kill": 0,
      "t1": 0,
      "t2": 0,
      "t3": 0,
      "t4": 0,
      "t5": 0,
      "help": 0,
      "dt": "2026/03/06",
      "dead_t1": 0,
      "dead_t2": 0,
      "dead_t3": 0,
      "dead_t4": 0,
      "dead_t5": 0
    }
  ]
}